LABS/student_labs_5_8/lab7_bus_arbiter/src/slave_sync.vhd
library ieee;
use ieee.std_logic_1164.all;
use work.lab_variant_pkg.all;

entity slave_sync is
  port (
    clk_i    : in  std_logic;
    rst_i    : in  std_logic;
    strobe_i : in  std_logic;
    data_i   : in  word_t;
    data_o   : out word_t;
    valid_o  : out std_logic
  );
end entity;

architecture rtl of slave_sync is
  signal data_r  : word_t := (others => '0');
  signal valid_r : std_logic := '0';
begin
  process(clk_i)
  begin
    if rising_edge(clk_i) then
      if rst_i = '1' then
        data_r  <= (others => '0');
        valid_r <= '0';
      else
        valid_r <= strobe_i;
        if strobe_i = '1' then
          data_r <= data_i;
        end if;
      end if;
    end if;
  end process;

  data_o  <= data_r;
  valid_o <= valid_r;
end architecture;

LABS/student_labs_5_8/lab7_bus_arbiter/src/bus_mux_4.vhd
library ieee;
use ieee.std_logic_1164.all;
use work.lab_variant_pkg.all;

entity bus_mux_4 is
  port (
    grant_i : in  std_logic_vector(3 downto 0);
    data0_i : in  word_t;
    data1_i : in  word_t;
    data2_i : in  word_t;
    data3_i : in  word_t;
    bus_o   : out word_t
  );
end entity;

architecture rtl of bus_mux_4 is
begin
  process(grant_i, data0_i, data1_i, data2_i, data3_i)
  begin
    bus_o <= (others => '0');
    if grant_i(0) = '1' then
      bus_o <= data0_i;
    elsif grant_i(1) = '1' then
      bus_o <= data1_i;
    elsif grant_i(2) = '1' then
      bus_o <= data2_i;
    elsif grant_i(3) = '1' then
      bus_o <= data3_i;
    end if;
  end process;
end architecture;

LABS/student_labs_5_8/lab7_bus_arbiter/src/bus_arbiter_parallel_quantum.vhd
library ieee;
use ieee.std_logic_1164.all;
use ieee.numeric_std.all;

entity bus_arbiter_parallel_quantum is
  generic (
    QUANTUM_CYCLES : positive := 2
  );
  port (
    clk_i          : in  std_logic;
    rst_i          : in  std_logic;
    req_i          : in  std_logic_vector(3 downto 0);
    grant_o        : out std_logic_vector(3 downto 0);
    slot_o         : out unsigned(1 downto 0);
    quantum_tick_o : out std_logic;
    busy_o         : out std_logic
  );
end entity;

architecture rtl of bus_arbiter_parallel_quantum is
  signal slot_r     : unsigned(1 downto 0) := (others => '0');
  signal quantum_r  : integer range 0 to QUANTUM_CYCLES - 1 := 0;
  signal grant_s    : std_logic_vector(3 downto 0);
  signal tick_s     : std_logic;
begin
  process(req_i, slot_r)
  begin
    grant_s <= (others => '0');
    if req_i(to_integer(slot_r)) = '1' then
      grant_s(to_integer(slot_r)) <= '1';
    end if;
  end process;

  process(clk_i)
  begin
    if rising_edge(clk_i) then
      if rst_i = '1' then
        slot_r    <= (others => '0');
        quantum_r <= 0;
      elsif quantum_r = QUANTUM_CYCLES - 1 then
        quantum_r <= 0;
        slot_r    <= slot_r + 1;
      else
        quantum_r <= quantum_r + 1;
      end if;
    end if;
  end process;

  tick_s <= '1' when quantum_r = QUANTUM_CYCLES - 1 else '0';

  grant_o        <= grant_s;
  slot_o         <= slot_r;
  quantum_tick_o <= tick_s;
  busy_o         <= '1' when grant_s /= "0000" else '0';
end architecture;

LABS/student_labs_5_8/lab7_bus_arbiter/src/master_device.vhd
library ieee;
use ieee.std_logic_1164.all;
use ieee.numeric_std.all;
use work.lab_variant_pkg.all;

entity master_device is
  generic (
    ID_VALUE    : natural := 1;
    START_CYCLE : natural := 1;
    HOLD_CYCLES : natural := 8
  );
  port (
    clk_i   : in  std_logic;
    rst_i   : in  std_logic;
    grant_i : in  std_logic;
    req_o   : out std_logic;
    data_o  : out word_t;
    used_o  : out std_logic
  );
end entity;

architecture rtl of master_device is
  signal cycle_r : natural range 0 to 255 := 0;
  signal req_s   : std_logic;
  signal used_r  : std_logic := '0';
begin
  req_s <= '1' when cycle_r >= START_CYCLE and cycle_r < START_CYCLE + HOLD_CYCLES else '0';

  process(clk_i)
  begin
    if rising_edge(clk_i) then
      if rst_i = '1' then
        cycle_r <= 0;
        used_r  <= '0';
      else
        if cycle_r < 255 then
          cycle_r <= cycle_r + 1;
        end if;
        if grant_i = '1' then
          used_r <= '1';
        end if;
      end if;
    end if;
  end process;

  req_o  <= req_s;
  data_o <= std_logic_vector(to_unsigned(ID_VALUE, DATA_W));
  used_o <= used_r;
end architecture;

LABS/student_labs_5_8/lab7_bus_arbiter/src/lab7_bus_top.vhd
library ieee;
use ieee.std_logic_1164.all;
use ieee.numeric_std.all;
use work.lab_variant_pkg.all;

entity lab7_bus_top is
  port (
    clk_i       : in  std_logic;
    rst_i       : in  std_logic;
    req_o       : out std_logic_vector(3 downto 0);
    grant_o     : out std_logic_vector(3 downto 0);
    bus_data_o  : out word_t;
    slave_data_o: out word_t;
    slave_valid_o: out std_logic;
    slot_o      : out unsigned(1 downto 0);
    used_o      : out std_logic_vector(3 downto 0)
  );
end entity;

architecture structural of lab7_bus_top is
  signal req_s        : std_logic_vector(3 downto 0);
  signal grant_s      : std_logic_vector(3 downto 0);
  signal data0_s      : word_t;
  signal data1_s      : word_t;
  signal data2_s      : word_t;
  signal data3_s      : word_t;
  signal bus_s        : word_t;
  signal busy_s       : std_logic;
  signal tick_s       : std_logic;
begin
  U_MASTER0 : entity work.master_device
    generic map (ID_VALUE => 16#1111#, START_CYCLE => 1, HOLD_CYCLES => 10)
    port map (clk_i => clk_i, rst_i => rst_i, grant_i => grant_s(0), req_o => req_s(0), data_o => data0_s, used_o => used_o(0));

  U_MASTER1 : entity work.master_device
    generic map (ID_VALUE => 16#2222#, START_CYCLE => 2, HOLD_CYCLES => 10)
    port map (clk_i => clk_i, rst_i => rst_i, grant_i => grant_s(1), req_o => req_s(1), data_o => data1_s, used_o => used_o(1));

  U_MASTER2 : entity work.master_device
    generic map (ID_VALUE => 16#3333#, START_CYCLE => 4, HOLD_CYCLES => 10)
    port map (clk_i => clk_i, rst_i => rst_i, grant_i => grant_s(2), req_o => req_s(2), data_o => data2_s, used_o => used_o(2));

  U_MASTER3 : entity work.master_device
    generic map (ID_VALUE => 16#4444#, START_CYCLE => 6, HOLD_CYCLES => 10)
    port map (clk_i => clk_i, rst_i => rst_i, grant_i => grant_s(3), req_o => req_s(3), data_o => data3_s, used_o => used_o(3));

  U_ARBITER : entity work.bus_arbiter_parallel_quantum
    generic map (QUANTUM_CYCLES => 2)
    port map (
      clk_i          => clk_i,
      rst_i          => rst_i,
      req_i          => req_s,
      grant_o        => grant_s,
      slot_o         => slot_o,
      quantum_tick_o => tick_s,
      busy_o         => busy_s
    );

  U_BUS : entity work.bus_mux_4
    port map (
      grant_i => grant_s,
      data0_i => data0_s,
      data1_i => data1_s,
      data2_i => data2_s,
      data3_i => data3_s,
      bus_o   => bus_s
    );

  U_SLAVE : entity work.slave_sync
    port map (
      clk_i    => clk_i,
      rst_i    => rst_i,
      strobe_i => busy_s,
      data_i   => bus_s,
      data_o   => slave_data_o,
      valid_o  => slave_valid_o
    );

  req_o      <= req_s;
  grant_o    <= grant_s;
  bus_data_o <= bus_s;
end architecture;

LABS/student_labs_5_8/lab7_bus_arbiter/src/lab7_bus_rtl_view_top.vhd
library ieee;
use ieee.std_logic_1164.all;
use ieee.numeric_std.all;
use work.lab_variant_pkg.all;

entity lab7_bus_rtl_view_top is
  port (
    clock_i                            : in  std_logic;
    reset_i                            : in  std_logic;
    master_bus_request_lines_o         : out std_logic_vector(3 downto 0);
    arbiter_bus_grant_lines_o          : out std_logic_vector(3 downto 0);
    shared_data_bus_to_slave_o         : out word_t;
    slave_latched_data_from_bus_o      : out word_t;
    slave_data_valid_strobe_o          : out std_logic;
    current_time_quantum_slot_o        : out unsigned(1 downto 0);
    master_was_serviced_debug_o        : out std_logic_vector(3 downto 0)
  );
end entity;

architecture structural of lab7_bus_rtl_view_top is
begin
  U_BUS_SYSTEM : entity work.lab7_bus_top
    port map (
      clk_i         => clock_i,
      rst_i         => reset_i,
      req_o         => master_bus_request_lines_o,
      grant_o       => arbiter_bus_grant_lines_o,
      bus_data_o    => shared_data_bus_to_slave_o,
      slave_data_o  => slave_latched_data_from_bus_o,
      slave_valid_o => slave_data_valid_strobe_o,
      slot_o        => current_time_quantum_slot_o,
      used_o        => master_was_serviced_debug_o
    );
end architecture;

LABS/student_labs_5_8/lab7_bus_arbiter/quartus/db/lab7_bus_arbiter.sim.vcd
$comment
Copyright (C) 1991-2009 Altera Corporation
Your use of Altera Corporation's design tools, logic functions 
and other software and tools, and its AMPP partner logic 
functions, and any output files from any of the foregoing 
(including device programming or simulation files), and any 
associated documentation or information are expressly subject 
to the terms and conditions of the Altera Program License 
Subscription Agreement, Altera MegaCore Function License 
Agreement, or other applicable license agreement, including, 
without limitation, that your use is for the sole purpose of 
programming logic devices manufactured by Altera and sold by 
Altera or its authorized distributors.  Please refer to the 
applicable agreement for further details.
$end

$date 
  05/17/2026 17:16:47 
$end
$version 
 QUARTUS_VCD_EXPORT 1.0 
$end
$timescale
  1 ps
$end
$scope module lab7_bus_rtl_view_top $end
$var reg 1 ! clock_i $end
$var reg 1 " reset_i $end
$var reg 4 # master_bus_request_lines_o[3:0] $end
$var reg 4 $ arbiter_bus_grant_lines_o[3:0] $end
$var reg 16 % shared_data_bus_to_slave_o[15:0] $end
$var reg 16 & slave_latched_data_from_bus_o[15:0] $end
$var reg 1 ' slave_data_valid_strobe_o $end
$var reg 2 ( current_time_quantum_slot_o[1:0] $end
$var reg 4 ) master_was_serviced_debug_o[3:0] $end
$upscope $end
$enddefinitions $end
#0
$dumpvars
0!
1"
b0 #
b0 $
b0 %
b0 &
0'
b0 (
b0 )
$end
#5000
1!
#10000
0!
#15000
1!
#20000
0!
0"
#25000
1!
b1 #
b1 $
b1000100010001 %
#30000
0!
#35000
1!
b11 #
b10 $
b10001000100010 %
b1000100010001 &
1'
b1 (
b1 )
#40000
0!
#45000
1!
b10001000100010 &
b11 )
#50000
0!
#55000
1!
b111 #
b100 $
b11001100110011 %
b10 (
#60000
0!
#65000
1!
b11001100110011 &
b111 )
#70000
0!
#75000
1!
b1111 #
b1000 $
b100010001000100 %
b11 (
#80000
0!
#85000
1!
b100010001000100 &
b1111 )
#90000
0!
#95000
1!
b1 $
b1000100010001 %
b0 (
#100000
0!
#105000
1!
b1000100010001 &
#110000
0!
#115000
1!
b10 $
b10001000100010 %
b1 (
#120000
0!
#125000
1!
b1110 #
b10001000100010 &
#130000
0!
#135000
1!
b1100 #
b100 $
b11001100110011 %
b10 (
#140000
0!
#145000
1!
b11001100110011 &
#150000
0!
#155000
1!
b1000 #
b1000 $
b100010001000100 %
b11 (
#160000
0!
#165000
1!
b100010001000100 &
#170000
0!
#175000
1!
b0 #
b0 $
b0 %
b0 (
#180000
0!
#185000
1!
0'
#190000
0!
#195000
1!
b1 (
#200000
0!
#205000
1!
#210000
0!
#215000
1!
b10 (
