LABS/student_labs_5_8/lab6_stack/src/stack7x16.vhd
library ieee;
use ieee.std_logic_1164.all;
use ieee.numeric_std.all;
use work.lab_variant_pkg.all;

entity stack7x16 is
  port (
    clk_i       : in  std_logic;
    rst_i       : in  std_logic;
    push_i      : in  std_logic;
    pop_i       : in  std_logic;
    din_i       : in  word_t;
    dout_o      : out word_t;
    sp_o        : out unsigned(2 downto 0);
    empty_o     : out std_logic;
    full_o      : out std_logic;
    overflow_o  : out std_logic;
    underflow_o : out std_logic
  );
end entity;

architecture rtl of stack7x16 is
  type stack_mem_t is array (0 to STACK_DEPTH - 1) of word_t;
  signal mem_r       : stack_mem_t := (others => (others => '0'));
  signal sp_r        : unsigned(2 downto 0) := to_unsigned(STACK_DEPTH, 3);
  signal dout_r      : word_t := (others => '0');
  signal overflow_r  : std_logic := '0';
  signal underflow_r : std_logic := '0';
begin
  dout_o      <= dout_r;
  sp_o        <= sp_r;
  empty_o     <= '1' when sp_r = to_unsigned(STACK_DEPTH, 3) else '0';
  full_o      <= '1' when sp_r = to_unsigned(STACK_DEPTH - 1, 3) else '0';
  overflow_o  <= overflow_r;
  underflow_o <= underflow_r;

  process(clk_i)
    variable sp_v : integer;
  begin
    if rising_edge(clk_i) then
      if rst_i = '1' then
        mem_r       <= (others => (others => '0'));
        sp_r        <= to_unsigned(STACK_DEPTH, 3);
        dout_r      <= (others => '0');
        overflow_r  <= '0';
        underflow_r <= '0';
      else
        overflow_r  <= '0';
        underflow_r <= '0';
        sp_v := to_integer(sp_r);

        if push_i = '1' and pop_i = '0' then
          if sp_v = STACK_DEPTH - 1 then
            overflow_r <= '1';
          elsif sp_v = STACK_DEPTH then
            mem_r(0) <= din_i;
            sp_r <= to_unsigned(0, 3);
          else
            mem_r(sp_v + 1) <= din_i;
            sp_r <= to_unsigned(sp_v + 1, 3);
          end if;
        elsif pop_i = '1' and push_i = '0' then
          if sp_v = STACK_DEPTH then
            underflow_r <= '1';
          else
            dout_r <= mem_r(sp_v);
            if sp_v = 0 then
              sp_r <= to_unsigned(STACK_DEPTH, 3);
            else
              sp_r <= to_unsigned(sp_v - 1, 3);
            end if;
          end if;
        end if;
      end if;
    end if;
  end process;
end architecture;

LABS/student_labs_5_8/lab6_stack/src/stack_control.vhd
library ieee;
use ieee.std_logic_1164.all;
use work.lab_variant_pkg.all;

entity stack_control is
  port (
    cmd_i      : in  std_logic_vector(1 downto 0);
    push_o     : out std_logic;
    pop_o      : out std_logic;
    alu_src_o  : out std_logic
  );
end entity;

architecture rtl of stack_control is
begin
  process(cmd_i)
  begin
    push_o    <= '0';
    pop_o     <= '0';
    alu_src_o <= '0';

    case cmd_i is
      when STACK_PUSH_REG =>
        push_o <= '1';
      when STACK_POP_REG =>
        pop_o <= '1';
      when STACK_PUSH_ALU =>
        push_o    <= '1';
        alu_src_o <= '1';
      when others =>
        null;
    end case;
  end process;
end architecture;

LABS/student_labs_5_8/lab6_stack/src/lab6_stack_top.vhd
library ieee;
use ieee.std_logic_1164.all;
use ieee.numeric_std.all;
use work.lab_variant_pkg.all;

entity lab6_stack_top is
  port (
    clk_i       : in  std_logic;
    rst_i       : in  std_logic;
    cmd_i       : in  std_logic_vector(1 downto 0);
    reg_data_i  : in  word_t;
    alu_data_i  : in  word_t;
    stack_out_o : out word_t;
    sp_o        : out unsigned(2 downto 0);
    empty_o     : out std_logic;
    full_o      : out std_logic;
    overflow_o  : out std_logic;
    underflow_o : out std_logic;
    push_dbg_o  : out std_logic;
    pop_dbg_o   : out std_logic
  );
end entity;

architecture structural of lab6_stack_top is
  signal push_s   : std_logic;
  signal pop_s    : std_logic;
  signal alu_src_s: std_logic;
  signal din_s    : word_t;
begin
  U_CTRL : entity work.stack_control
    port map (
      cmd_i     => cmd_i,
      push_o    => push_s,
      pop_o     => pop_s,
      alu_src_o => alu_src_s
    );

  din_s <= alu_data_i when alu_src_s = '1' else reg_data_i;

  U_STACK : entity work.stack7x16
    port map (
      clk_i       => clk_i,
      rst_i       => rst_i,
      push_i      => push_s,
      pop_i       => pop_s,
      din_i       => din_s,
      dout_o      => stack_out_o,
      sp_o        => sp_o,
      empty_o     => empty_o,
      full_o      => full_o,
      overflow_o  => overflow_o,
      underflow_o => underflow_o
    );

  push_dbg_o <= push_s;
  pop_dbg_o  <= pop_s;
end architecture;

LABS/student_labs_5_8/lab6_stack/src/lab6_stack_rtl_view_top.vhd
library ieee;
use ieee.std_logic_1164.all;
use ieee.numeric_std.all;
use work.lab_variant_pkg.all;

entity lab6_stack_rtl_view_top is
  port (
    clock_i                         : in  std_logic;
    reset_i                         : in  std_logic;
    stack_command_idle_push_pop_i   : in  std_logic_vector(1 downto 0);
    data_from_register_file_i       : in  word_t;
    alu_result_for_push_i           : in  word_t;
    data_popped_to_register_file_o  : out word_t;
    stack_pointer_current_value_o   : out unsigned(2 downto 0);
    status_stack_empty_o            : out std_logic;
    status_stack_full_o             : out std_logic;
    error_push_to_full_stack_o      : out std_logic;
    error_pop_from_empty_stack_o    : out std_logic;
    ctrl_push_enable_o              : out std_logic;
    ctrl_pop_enable_o               : out std_logic
  );
end entity;

architecture structural of lab6_stack_rtl_view_top is
begin
  U_STACK_SYSTEM : entity work.lab6_stack_top
    port map (
      clk_i       => clock_i,
      rst_i       => reset_i,
      cmd_i       => stack_command_idle_push_pop_i,
      reg_data_i  => data_from_register_file_i,
      alu_data_i  => alu_result_for_push_i,
      stack_out_o => data_popped_to_register_file_o,
      sp_o        => stack_pointer_current_value_o,
      empty_o     => status_stack_empty_o,
      full_o      => status_stack_full_o,
      overflow_o  => error_push_to_full_stack_o,
      underflow_o => error_pop_from_empty_stack_o,
      push_dbg_o  => ctrl_push_enable_o,
      pop_dbg_o   => ctrl_pop_enable_o
    );
end architecture;

LABS/student_labs_5_8/lab6_stack/quartus/db/lab6_stack.sim.vcd
$comment
Copyright (C) 1991-2009 Altera Corporation
Your use of Altera Corporation's design tools, logic functions 
and other software and tools, and its AMPP partner logic 
functions, and any output files from any of the foregoing 
(including device programming or simulation files), and any 
associated documentation or information are expressly subject 
to the terms and conditions of the Altera Program License 
Subscription Agreement, Altera MegaCore Function License 
Agreement, or other applicable license agreement, including, 
without limitation, that your use is for the sole purpose of 
programming logic devices manufactured by Altera and sold by 
Altera or its authorized distributors.  Please refer to the 
applicable agreement for further details.
$end

$date 
  05/17/2026 15:33:10 
$end
$version 
 QUARTUS_VCD_EXPORT 1.0 
$end
$timescale
  1 ps
$end
$scope module lab6_stack_rtl_view_top $end
$var reg 1 ! clock_i $end
$var reg 1 " reset_i $end
$var reg 2 # stack_command_idle_push_pop_i[1:0] $end
$var reg 16 $ data_from_register_file_i[15:0] $end
$var reg 16 % alu_result_for_push_i[15:0] $end
$var reg 16 & data_popped_to_register_file_o[15:0] $end
$var reg 3 ' stack_pointer_current_value_o[2:0] $end
$var reg 1 ( status_stack_empty_o $end
$var reg 1 ) status_stack_full_o $end
$var reg 1 * error_push_to_full_stack_o $end
$var reg 1 + error_pop_from_empty_stack_o $end
$var reg 1 , ctrl_push_enable_o $end
$var reg 1 - ctrl_pop_enable_o $end
$upscope $end
$enddefinitions $end
#0
$dumpvars
0!
1"
b0 #
b0 $
b0 %
b0 &
b111 '
1(
0)
0*
0+
0,
0-
$end
#5000
1!
#10000
0!
#15000
1!
#20000
0!
0"
b1 #
b1000100010001 $
1,
#25000
1!
b0 '
0(
#30000
0!
b10001000100010 $
#35000
1!
b1 '
#40000
0!
b10 #
0,
1-
#45000
1!
b10001000100010 &
b0 '
#50000
0!
b11 #
b1111 %
1,
0-
#55000
1!
b1 '
#60000
0!
b1 #
b11001100110011 $
#65000
1!
b10 '
#70000
0!
b100010001000100 $
#75000
1!
b11 '
#80000
0!
b101010101010101 $
#85000
1!
b100 '
#90000
0!
b110011001100110 $
#95000
1!
b101 '
#100000
0!
b111011101110111 $
#105000
1!
b110 '
1)
#110000
0!
b1000100010001000 $
#115000
1!
1*
#120000
0!
b10 #
0,
1-
#125000
1!
b111011101110111 &
b101 '
0)
0*
#130000
0!
#135000
1!
b110011001100110 &
b100 '
#140000
0!
#145000
1!
b101010101010101 &
b11 '
#150000
0!
#155000
1!
b100010001000100 &
b10 '
#160000
0!
#165000
1!
b11001100110011 &
b1 '
#170000
0!
#175000
1!
b1111 &
b0 '
#180000
0!
#185000
1!
b1000100010001 &
b111 '
1(
#190000
0!
#195000
1!
1+
#200000
0!
b0 #
0-
#205000
1!
0+
