coursework_project/src/ram_sync.vhd
library ieee;
use ieee.std_logic_1164.all;
use ieee.numeric_std.all;
use work.microcomputer_pkg.all;
use work.data_image_pkg.all;

entity ram_sync is
  port (
    clk_i  : in  std_logic;
    en_i   : in  std_logic;
    we_i   : in  std_logic;
    addr_i : in  addr_t;
    din_i  : in  word_t;
    dout_o : out word_t
  );
end entity;

architecture rtl of ram_sync is
  signal mem : ram256_t := RAM_INIT;
  signal q_r : word_t := (others => '0');
begin
  dout_o <= q_r;

  process(clk_i)
    variable idx : integer;
  begin
    if rising_edge(clk_i) then
      if en_i = '1' then
        idx := to_integer(unsigned(addr_i(7 downto 0)));
        if we_i = '1' then
          mem(idx) <= din_i;
        end if;
        q_r <= mem(idx);
      end if;
    end if;
  end process;
end architecture;

coursework_project/src/dma_controller_3word.vhd
library ieee;
use ieee.std_logic_1164.all;
use ieee.numeric_std.all;
use work.microcomputer_pkg.all;

entity dma_controller_3word is
  generic (
    BASE_ADDR_G : addr_t := x"000A"
  );
  port (
    clk_i       : in  std_logic;
    rst_i       : in  std_logic;
    start_i     : in  std_logic;
    grant_i     : in  std_logic;
    dev_valid_i : in  std_logic;
    dev_data_i  : in  word_t;
    req_o       : out std_logic;
    busy_o      : out std_logic;
    done_o      : out std_logic;
    ram_we_o    : out std_logic;
    ram_addr_o  : out addr_t;
    ram_data_o  : out word_t
  );
end entity;

architecture rtl of dma_controller_3word is
  type state_t is (IDLE, REQ_BUS, WRITE_WORD, FINISH);
  signal state_r  : state_t := IDLE;
  signal index_r  : unsigned(1 downto 0) := (others => '0');
  signal done_r   : std_logic := '0';
begin
  busy_o     <= '0' when state_r = IDLE else '1';
  req_o      <= '1' when state_r = REQ_BUS or state_r = WRITE_WORD else '0';
  ram_we_o   <= '1' when state_r = WRITE_WORD and grant_i = '1' and dev_valid_i = '1' else '0';
  ram_addr_o <= std_logic_vector(unsigned(BASE_ADDR_G) + resize(index_r, ADDR_W));
  ram_data_o <= dev_data_i;
  done_o     <= done_r;

  process(clk_i)
  begin
    if rising_edge(clk_i) then
      if rst_i = '1' then
        state_r <= IDLE;
        index_r <= (others => '0');
        done_r  <= '0';
      else
        case state_r is
          when IDLE =>
            if start_i = '1' then
              index_r <= (others => '0');
              done_r  <= '0';
              state_r <= REQ_BUS;
            end if;
          when REQ_BUS =>
            if grant_i = '1' then
              state_r <= WRITE_WORD;
            end if;
          when WRITE_WORD =>
            if grant_i = '1' and dev_valid_i = '1' then
              if index_r = "10" then
                state_r <= FINISH;
              else
                index_r <= index_r + 1;
              end if;
            end if;
          when FINISH =>
            done_r  <= '1';
            state_r <= IDLE;
        end case;
      end if;
    end if;
  end process;
end architecture;

coursework_project/tb/tb_mem_dma.vhd
library ieee;
use ieee.std_logic_1164.all;
use ieee.numeric_std.all;
use work.microcomputer_pkg.all;

entity tb_mem_dma is
end entity;

architecture sim of tb_mem_dma is
  signal clk      : std_logic := '0';
  signal rst      : std_logic := '1';
  signal start    : std_logic := '0';
  signal dev_valid: std_logic := '0';
  signal dev_data : word_t    := (others => '0');
  signal dma_req  : std_logic;
  signal dma_gnt  : std_logic;
  signal dma_done : std_logic;
  signal ram_we   : std_logic;
  signal ram_addr : addr_t;
  signal ram_din  : word_t;
  signal ram_dout : word_t;
begin
  clk <= not clk after 5 ns;
  dma_gnt <= dma_req;

  U_DMA : entity work.dma_controller_3word
    port map (
      clk_i => clk,
      rst_i => rst,
      start_i => start,
      grant_i => dma_gnt,
      dev_valid_i => dev_valid,
      dev_data_i => dev_data,
      req_o => dma_req,
      busy_o => open,
      done_o => dma_done,
      ram_we_o => ram_we,
      ram_addr_o => ram_addr,
      ram_data_o => ram_din
    );

  U_RAM : entity work.ram_sync
    port map (
      clk_i => clk,
      en_i => '1',
      we_i => ram_we,
      addr_i => ram_addr,
      din_i => ram_din,
      dout_o => ram_dout
    );

  monitor : process(clk)
    variable write_count : integer := 0;
  begin
    if rising_edge(clk) then
      if rst = '1' then
        write_count := 0;
      elsif ram_we = '1' then
        case write_count is
          when 0 =>
            assert ram_addr = x"000A" and ram_din = x"1111"
              report "DMA first write must target 000Ah with 1111h" severity failure;
          when 1 =>
            assert ram_addr = x"000B" and ram_din = x"2222"
              report "DMA second write must target 000Bh with 2222h" severity failure;
          when 2 =>
            assert ram_addr = x"000C" and ram_din = x"3333"
              report "DMA third write must target 000Ch with 3333h" severity failure;
          when others =>
            assert false report "Unexpected extra DMA write" severity failure;
        end case;
        write_count := write_count + 1;
      end if;
    end if;
  end process;

  stimulus : process
  begin
    wait for 30 ns;
    rst <= '0';

    wait until rising_edge(clk);
    start    <= '1';
    dev_valid <= '1';
    dev_data <= x"1111";
    wait until rising_edge(clk);
    start <= '0';

    wait until rising_edge(clk);
    dev_data <= x"1111";
    wait until rising_edge(clk);
    dev_data <= x"2222";
    wait until rising_edge(clk);
    dev_data <= x"3333";
    wait until rising_edge(clk);
    dev_valid <= '0';
    wait until rising_edge(clk);
    wait for 1 ns;
    assert dma_done = '1'
      report "DMA must assert done after three words" severity failure;

    assert false report "tb_mem_dma: TEST PASSED" severity note;
    wait;
  end process;
end architecture;

coursework_project/sim/ghdl/tb_mem_dma.vcd
$date
  Tue Apr 28 21:24:18 2026
$end
$version
  GHDL v0
$end
$timescale
  1 fs
$end
$scope module standard $end
$upscope $end
$scope module textio $end
$upscope $end
$scope module std_logic_1164 $end
$upscope $end
$scope module numeric_std $end
$upscope $end
$scope module microcomputer_pkg $end
$upscope $end
$scope module data_image_pkg $end
$upscope $end
$scope module tb_mem_dma $end
$var reg 1 ! clk $end
$var reg 1 " rst $end
$var reg 1 # start $end
$var reg 1 $ dev_valid $end
$var reg 16 % dev_data[15:0] $end
$var reg 1 & dma_req $end
$var reg 1 ' dma_gnt $end
$var reg 1 ( dma_done $end
$var reg 1 ) ram_we $end
$var reg 16 * ram_addr[15:0] $end
$var reg 16 + ram_din[15:0] $end
$var reg 16 , ram_dout[15:0] $end
$scope module u_dma $end
$var reg 1 - clk_i $end
$var reg 1 . rst_i $end
$var reg 1 / start_i $end
$var reg 1 0 grant_i $end
$var reg 1 1 dev_valid_i $end
$var reg 16 2 dev_data_i[15:0] $end
$var reg 1 3 req_o $end
$var reg 1 4 busy_o $end
$var reg 1 5 done_o $end
$var reg 1 6 ram_we_o $end
$var reg 16 7 ram_addr_o[15:0] $end
$var reg 16 8 ram_data_o[15:0] $end
$comment state_r is not handled $end
$var reg 2 9 index_r[1:0] $end
$var reg 1 : done_r $end
$upscope $end
$scope module u_ram $end
$var reg 1 ; clk_i $end
$var reg 1 < en_i $end
$var reg 1 = we_i $end
$var reg 16 > addr_i[15:0] $end
$var reg 16 ? din_i[15:0] $end
$var reg 16 @ dout_o[15:0] $end
$comment mem is not handled $end
$var reg 16 A q_r[15:0] $end
$upscope $end
$upscope $end
$enddefinitions $end
#0
0!
1"
0#
0$
b0000000000000000 %
0&
0'
0(
0)
b0000000000001010 *
b0000000000000000 +
b0000000000000000 ,
0-
1.
0/
00
01
b0000000000000000 2
03
04
05
06
b0000000000001010 7
b0000000000000000 8
b00 9
0:
0;
1<
0=
b0000000000001010 >
b0000000000000000 ?
b0000000000000000 @
b0000000000000000 A
#5000000
1!
1-
1;
#10000000
0!
0-
0;
#15000000
1!
1-
1;
#20000000
0!
0-
0;
#25000000
1!
1-
1;
#30000000
0!
0"
0-
0.
0;
#35000000
1!
1#
1$
b0001000100010001 %
b0001000100010001 +
1-
1/
11
b0001000100010001 2
b0001000100010001 8
1;
b0001000100010001 ?
#40000000
0!
0-
0;
#45000000
1!
0#
1&
1'
1-
0/
10
13
14
1;
#50000000
0!
0-
0;
#55000000
1!
1)
1-
16
1;
1=
#60000000
0!
0-
0;
#65000000
1!
b0010001000100010 %
b0000000000001011 *
b0010001000100010 +
1-
b0010001000100010 2
b0000000000001011 7
b0010001000100010 8
b01 9
1;
b0000000000001011 >
b0010001000100010 ?
#70000000
0!
0-
0;
#75000000
1!
b0011001100110011 %
b0000000000001100 *
b0011001100110011 +
1-
b0011001100110011 2
b0000000000001100 7
b0011001100110011 8
b10 9
1;
b0000000000001100 >
b0011001100110011 ?
#80000000
0!
0-
0;
#85000000
1!
0$
0&
0'
0)
1-
00
01
03
06
1;
0=
#90000000
0!
0-
0;
#95000000
1!
1(
b0011001100110011 ,
1-
04
15
1:
1;
b0011001100110011 @
b0011001100110011 A
