coursework_project/src/stack7x16.vhd
library ieee;
use ieee.std_logic_1164.all;
use ieee.numeric_std.all;
use work.microcomputer_pkg.all;

entity stack7x16 is
  port (
    clk_i   : in  std_logic;
    rst_i   : in  std_logic;
    push_i  : in  std_logic;
    pop_i   : in  std_logic;
    din_i   : in  word_t;
    dout_o  : out word_t;
    sp_o    : out unsigned(2 downto 0);
    empty_o : out std_logic;
    full_o  : out std_logic
  );
end entity;

architecture rtl of stack7x16 is
  type stack_mem_t is array (0 to STACK_DEPTH-1) of word_t;
  signal mem    : stack_mem_t := (others => (others => '0'));
  signal sp_r   : unsigned(2 downto 0) := to_unsigned(STACK_DEPTH, 3);
  signal dout_r : word_t := (others => '0');
begin
  dout_o  <= dout_r;
  sp_o    <= sp_r;
  empty_o <= '1' when sp_r = to_unsigned(STACK_DEPTH, 3) else '0';
  full_o  <= '1' when sp_r = to_unsigned(0, 3) else '0';

  process(clk_i)
    variable sp_i : integer;
  begin
    if rising_edge(clk_i) then
      if rst_i = '1' then
        mem    <= (others => (others => '0'));
        sp_r   <= to_unsigned(STACK_DEPTH, 3);
        dout_r <= (others => '0');
      else
        sp_i := to_integer(sp_r);

        if push_i = '1' and pop_i = '0' then
          if sp_i > 0 then
            mem(sp_i - 1) <= din_i;
            sp_r <= to_unsigned(sp_i - 1, 3);
          end if;
        elsif pop_i = '1' and push_i = '0' then
          if sp_i < STACK_DEPTH then
            dout_r <= mem(sp_i);
            sp_r   <= to_unsigned(sp_i + 1, 3);
          end if;
        end if;
      end if;
    end if;
  end process;
end architecture;

coursework_project/tb/tb_stack7x16.vhd
library ieee;
use ieee.std_logic_1164.all;
use ieee.numeric_std.all;
use work.microcomputer_pkg.all;

entity tb_stack7x16 is
end entity;

architecture sim of tb_stack7x16 is
  signal clk   : std_logic := '0';
  signal rst   : std_logic := '1';
  signal push  : std_logic := '0';
  signal pop   : std_logic := '0';
  signal din   : word_t := (others => '0');
  signal dout  : word_t;
  signal sp    : unsigned(2 downto 0);
  signal empty : std_logic;
  signal full  : std_logic;
begin
  clk <= not clk after 5 ns;

  DUT : entity work.stack7x16
    port map (
      clk_i => clk,
      rst_i => rst,
      push_i => push,
      pop_i => pop,
      din_i => din,
      dout_o => dout,
      sp_o => sp,
      empty_o => empty,
      full_o => full
    );

  stimulus : process
  begin
    wait for 12 ns;
    rst <= '0';
    wait for 1 ns;
    assert sp = to_unsigned(7, 3) and empty = '1' and full = '0'
      report "After reset stack must be empty with SP=7" severity failure;

    din <= x"0002"; push <= '1'; wait for 10 ns; push <= '0';
    din <= x"0006"; push <= '1'; wait for 10 ns; push <= '0';
    din <= x"0007"; push <= '1'; wait for 10 ns; push <= '0';
    din <= x"0078"; push <= '1'; wait for 10 ns; push <= '0';
    din <= x"03E0"; push <= '1'; wait for 10 ns; push <= '0';
    wait for 1 ns;
    assert sp = to_unsigned(2, 3)
      report "After five pushes SP must be 2" severity failure;

    pop <= '1'; wait for 10 ns; pop <= '0';
    wait for 1 ns;
    assert dout = x"03E0"
      report "First pop must return last pushed value 03E0h" severity failure;
    pop <= '1'; wait for 10 ns; pop <= '0';
    pop <= '1'; wait for 10 ns; pop <= '0';
    pop <= '1'; wait for 10 ns; pop <= '0';
    pop <= '1'; wait for 10 ns; pop <= '0';
    wait for 1 ns;
    assert sp = to_unsigned(7, 3) and empty = '1'
      report "After five pops stack must be empty with SP=7" severity failure;

    assert false report "tb_stack7x16: TEST PASSED" severity note;
    wait;
  end process;
end architecture;

coursework_project/sim/ghdl/tb_stack7x16.vcd
$date
  Tue Apr 28 21:24:17 2026
$end
$version
  GHDL v0
$end
$timescale
  1 fs
$end
$scope module standard $end
$upscope $end
$scope module textio $end
$upscope $end
$scope module std_logic_1164 $end
$upscope $end
$scope module numeric_std $end
$upscope $end
$scope module microcomputer_pkg $end
$upscope $end
$scope module tb_stack7x16 $end
$var reg 1 ! clk $end
$var reg 1 " rst $end
$var reg 1 # push $end
$var reg 1 $ pop $end
$var reg 16 % din[15:0] $end
$var reg 16 & dout[15:0] $end
$var reg 3 ' sp[2:0] $end
$var reg 1 ( empty $end
$var reg 1 ) full $end
$scope module dut $end
$var reg 1 * clk_i $end
$var reg 1 + rst_i $end
$var reg 1 , push_i $end
$var reg 1 - pop_i $end
$var reg 16 . din_i[15:0] $end
$var reg 16 / dout_o[15:0] $end
$var reg 3 0 sp_o[2:0] $end
$var reg 1 1 empty_o $end
$var reg 1 2 full_o $end
$comment mem is not handled $end
$var reg 3 3 sp_r[2:0] $end
$var reg 16 4 dout_r[15:0] $end
$upscope $end
$upscope $end
$enddefinitions $end
#0
0!
1"
0#
0$
b0000000000000000 %
b0000000000000000 &
b111 '
1(
0)
0*
1+
0,
0-
b0000000000000000 .
b0000000000000000 /
b111 0
11
02
b111 3
b0000000000000000 4
#5000000
1!
1*
#10000000
0!
0*
#12000000
0"
0+
#13000000
1#
b0000000000000010 %
1,
b0000000000000010 .
#15000000
1!
b110 '
0(
1*
b110 0
01
b110 3
#20000000
0!
0*
#23000000
b0000000000000110 %
b0000000000000110 .
#25000000
1!
b101 '
1*
b101 0
b101 3
#30000000
0!
0*
#33000000
b0000000000000111 %
b0000000000000111 .
#35000000
1!
b100 '
1*
b100 0
b100 3
#40000000
0!
0*
#43000000
b0000000001111000 %
b0000000001111000 .
#45000000
1!
b011 '
1*
b011 0
b011 3
#50000000
0!
0*
#53000000
b0000001111100000 %
b0000001111100000 .
#55000000
1!
b010 '
1*
b010 0
b010 3
#60000000
0!
0*
#63000000
0#
0,
#64000000
1$
1-
#65000000
1!
b0000001111100000 &
b011 '
1*
b0000001111100000 /
b011 0
b011 3
b0000001111100000 4
#70000000
0!
0*
#74000000
0$
0-
#75000000
1!
1$
1*
1-
#80000000
0!
0*
#85000000
1!
b0000000001111000 &
b100 '
1*
b0000000001111000 /
b100 0
b100 3
b0000000001111000 4
#90000000
0!
0*
#95000000
1!
b0000000000000111 &
b101 '
1*
b0000000000000111 /
b101 0
b101 3
b0000000000000111 4
#100000000
0!
0*
#105000000
1!
b0000000000000110 &
b110 '
1*
b0000000000000110 /
b110 0
b110 3
b0000000000000110 4
#110000000
0!
0*
#115000000
1!
0$
b0000000000000010 &
b111 '
1(
1*
0-
b0000000000000010 /
b111 0
11
b111 3
b0000000000000010 4
