LABS/student_labs_5_8/lab8_cache/src/main_memory_sync.vhd
library ieee;
use ieee.std_logic_1164.all;
use ieee.numeric_std.all;
use work.lab_variant_pkg.all;

entity main_memory_sync is
  port (
    clk_i   : in  std_logic;
    req_i   : in  std_logic;
    we_i    : in  std_logic;
    addr_i  : in  addr_t;
    wdata_i : in  word_t;
    rdata_o : out word_t;
    grant_o : out std_logic
  );
end entity;

architecture rtl of main_memory_sync is
  type mem_t is array (0 to 255) of word_t;

  function init_mem return mem_t is
    variable m : mem_t;
  begin
    for i in 0 to 255 loop
      m(i) := std_logic_vector(to_unsigned(16#1000# + i * 17, DATA_W));
    end loop;
    return m;
  end function;

  signal mem_r   : mem_t := init_mem;
  signal rdata_r : word_t := (others => '0');
  signal grant_r : std_logic := '0';
begin
  process(clk_i)
    variable idx_v : integer range 0 to 255;
  begin
    if rising_edge(clk_i) then
      grant_r <= req_i;
      idx_v := to_integer(unsigned(addr_i(7 downto 0)));
      if req_i = '1' then
        if we_i = '1' then
          mem_r(idx_v) <= wdata_i;
          rdata_r <= wdata_i;
        else
          rdata_r <= mem_r(idx_v);
        end if;
      end if;
    end if;
  end process;

  rdata_o <= rdata_r;
  grant_o <= grant_r;
end architecture;

LABS/student_labs_5_8/lab8_cache/src/cache_direct_mapped.vhd
library ieee;
use ieee.std_logic_1164.all;
use ieee.numeric_std.all;
use work.lab_variant_pkg.all;

entity cache_direct_mapped is
  port (
    clk_i        : in  std_logic;
    rst_i        : in  std_logic;
    cpu_req_i    : in  std_logic;
    cpu_we_i     : in  std_logic;
    cpu_addr_i   : in  addr_t;
    cpu_wdata_i  : in  word_t;
    cpu_rdata_o  : out word_t;
    cpu_ready_o  : out std_logic;
    hit_o        : out std_logic;
    miss_o       : out std_logic;
    ram_req_o    : out std_logic;
    ram_we_o     : out std_logic;
    ram_addr_o   : out addr_t;
    ram_wdata_o  : out word_t;
    ram_rdata_i  : in  word_t;
    ram_grant_i  : in  std_logic
  );
end entity;

architecture rtl of cache_direct_mapped is
  subtype cache_tag_t is std_logic_vector(12 downto 0);
  type cache_state_t is (IDLE, WAIT_READ_GRANT, WAIT_READ_DATA, WAIT_WRITE_GRANT);
  type cache_data_t is array (0 to CACHE_SETS - 1) of word_t;
  type cache_tag_array_t is array (0 to CACHE_SETS - 1) of cache_tag_t;
  type cache_valid_t is array (0 to CACHE_SETS - 1) of std_logic;

  signal state_r      : cache_state_t := IDLE;
  signal data_r       : cache_data_t := (others => (others => '0'));
  signal tag_r        : cache_tag_array_t := (others => (others => '0'));
  signal valid_r      : cache_valid_t := (others => '0');
  signal req_addr_r   : addr_t := (others => '0');
  signal req_wdata_r  : word_t := (others => '0');
  signal index_r      : integer range 0 to CACHE_SETS - 1 := 0;
  signal tag_req_r    : cache_tag_t := (others => '0');
  signal cpu_rdata_r  : word_t := (others => '0');
  signal cpu_ready_r  : std_logic := '0';
  signal hit_r        : std_logic := '0';
  signal miss_r       : std_logic := '0';
  signal ram_req_r    : std_logic := '0';
  signal ram_we_r     : std_logic := '0';
  signal ram_addr_r   : addr_t := (others => '0');
  signal ram_wdata_r  : word_t := (others => '0');

  function cache_index(addr : addr_t) return integer is
  begin
    return to_integer(unsigned(addr(2 downto 0)));
  end function;

  function cache_tag(addr : addr_t) return cache_tag_t is
  begin
    return addr(15 downto 3);
  end function;
begin
  cpu_rdata_o <= cpu_rdata_r;
  cpu_ready_o <= cpu_ready_r;
  hit_o       <= hit_r;
  miss_o      <= miss_r;
  ram_req_o   <= ram_req_r;
  ram_we_o    <= ram_we_r;
  ram_addr_o  <= ram_addr_r;
  ram_wdata_o <= ram_wdata_r;

  process(clk_i)
    variable index_v : integer range 0 to CACHE_SETS - 1;
    variable tag_v   : cache_tag_t;
    variable hit_v   : boolean;
  begin
    if rising_edge(clk_i) then
      if rst_i = '1' then
        state_r     <= IDLE;
        data_r      <= (others => (others => '0'));
        tag_r       <= (others => (others => '0'));
        valid_r     <= (others => '0');
        req_addr_r  <= (others => '0');
        req_wdata_r <= (others => '0');
        index_r     <= 0;
        tag_req_r   <= (others => '0');
        cpu_rdata_r <= (others => '0');
        cpu_ready_r <= '0';
        hit_r       <= '0';
        miss_r      <= '0';
        ram_req_r   <= '0';
        ram_we_r    <= '0';
        ram_addr_r  <= (others => '0');
        ram_wdata_r <= (others => '0');
      else
        cpu_ready_r <= '0';
        hit_r       <= '0';
        miss_r      <= '0';

        case state_r is
          when IDLE =>
            ram_req_r <= '0';
            ram_we_r  <= '0';

            if cpu_req_i = '1' then
              index_v := cache_index(cpu_addr_i);
              tag_v := cache_tag(cpu_addr_i);
              hit_v := valid_r(index_v) = '1' and tag_r(index_v) = tag_v;

              req_addr_r  <= cpu_addr_i;
              req_wdata_r <= cpu_wdata_i;
              index_r     <= index_v;
              tag_req_r   <= tag_v;

              if hit_v and cpu_we_i = '0' then
                cpu_rdata_r <= data_r(index_v);
                cpu_ready_r <= '1';
                hit_r       <= '1';
              elsif cpu_we_i = '1' then
                if hit_v then
                  hit_r <= '1';
                else
                  miss_r <= '1';
                end if;
                data_r(index_v)  <= cpu_wdata_i;
                tag_r(index_v)   <= tag_v;
                valid_r(index_v) <= '1';
                ram_req_r        <= '1';
                ram_we_r         <= '1';
                ram_addr_r       <= cpu_addr_i;
                ram_wdata_r      <= cpu_wdata_i;
                state_r          <= WAIT_WRITE_GRANT;
              else
                ram_req_r   <= '1';
                ram_we_r    <= '0';
                ram_addr_r  <= cpu_addr_i;
                ram_wdata_r <= (others => '0');
                state_r     <= WAIT_READ_GRANT;
                miss_r      <= '1';
              end if;
            end if;

          when WAIT_READ_GRANT =>
            ram_req_r  <= '1';
            ram_we_r   <= '0';
            ram_addr_r <= req_addr_r;
            if ram_grant_i = '1' then
              state_r <= WAIT_READ_DATA;
            end if;

          when WAIT_READ_DATA =>
            ram_req_r <= '0';
            ram_we_r  <= '0';
            data_r(index_r)  <= ram_rdata_i;
            tag_r(index_r)   <= tag_req_r;
            valid_r(index_r) <= '1';
            cpu_rdata_r      <= ram_rdata_i;
            cpu_ready_r      <= '1';
            miss_r           <= '1';
            state_r          <= IDLE;

          when WAIT_WRITE_GRANT =>
            ram_req_r   <= '1';
            ram_we_r    <= '1';
            ram_addr_r  <= req_addr_r;
            ram_wdata_r <= req_wdata_r;
            if ram_grant_i = '1' then
              cpu_ready_r <= '1';
              ram_req_r   <= '0';
              ram_we_r    <= '0';
              state_r     <= IDLE;
            end if;
        end case;
      end if;
    end if;
  end process;
end architecture;

LABS/student_labs_5_8/lab8_cache/src/lab8_cache_top.vhd
library ieee;
use ieee.std_logic_1164.all;
use work.lab_variant_pkg.all;

entity lab8_cache_top is
  port (
    clk_i          : in  std_logic;
    rst_i          : in  std_logic;
    cpu_req_i      : in  std_logic;
    cpu_we_i       : in  std_logic;
    cpu_addr_i     : in  addr_t;
    cpu_wdata_i    : in  word_t;
    cpu_rdata_o    : out word_t;
    cpu_ready_o    : out std_logic;
    hit_o          : out std_logic;
    miss_o         : out std_logic;
    ram_req_dbg_o  : out std_logic;
    ram_we_dbg_o   : out std_logic;
    ram_addr_dbg_o : out addr_t;
    ram_data_dbg_o : out word_t
  );
end entity;

architecture structural of lab8_cache_top is
  signal ram_req_s   : std_logic;
  signal ram_we_s    : std_logic;
  signal ram_addr_s  : addr_t;
  signal ram_wdata_s : word_t;
  signal ram_rdata_s : word_t;
  signal ram_grant_s : std_logic;
begin
  U_CACHE : entity work.cache_direct_mapped
    port map (
      clk_i        => clk_i,
      rst_i        => rst_i,
      cpu_req_i    => cpu_req_i,
      cpu_we_i     => cpu_we_i,
      cpu_addr_i   => cpu_addr_i,
      cpu_wdata_i  => cpu_wdata_i,
      cpu_rdata_o  => cpu_rdata_o,
      cpu_ready_o  => cpu_ready_o,
      hit_o        => hit_o,
      miss_o       => miss_o,
      ram_req_o    => ram_req_s,
      ram_we_o     => ram_we_s,
      ram_addr_o   => ram_addr_s,
      ram_wdata_o  => ram_wdata_s,
      ram_rdata_i  => ram_rdata_s,
      ram_grant_i  => ram_grant_s
    );

  U_RAM : entity work.main_memory_sync
    port map (
      clk_i   => clk_i,
      req_i   => ram_req_s,
      we_i    => ram_we_s,
      addr_i  => ram_addr_s,
      wdata_i => ram_wdata_s,
      rdata_o => ram_rdata_s,
      grant_o => ram_grant_s
    );

  ram_req_dbg_o  <= ram_req_s;
  ram_we_dbg_o   <= ram_we_s;
  ram_addr_dbg_o <= ram_addr_s;
  ram_data_dbg_o <= ram_wdata_s when ram_we_s = '1' else ram_rdata_s;
end architecture;

LABS/student_labs_5_8/lab8_cache/src/lab8_cache_rtl_view_top.vhd
library ieee;
use ieee.std_logic_1164.all;
use work.lab_variant_pkg.all;

entity lab8_cache_rtl_view_top is
  port (
    clock_i                              : in  std_logic;
    reset_i                              : in  std_logic;
    cpu_cache_request_i                  : in  std_logic;
    cpu_write_enable_i                   : in  std_logic;
    cpu_address_tag_set_i                : in  addr_t;
    cpu_write_data_to_cache_i            : in  word_t;
    cpu_read_data_from_cache_o           : out word_t;
    cpu_cache_response_ready_o           : out std_logic;
    cache_hit_signal_o                   : out std_logic;
    cache_miss_signal_o                  : out std_logic;
    memory_request_from_cache_debug_o    : out std_logic;
    memory_write_enable_debug_o          : out std_logic;
    memory_address_debug_o               : out addr_t;
    memory_data_debug_o                  : out word_t
  );
end entity;

architecture structural of lab8_cache_rtl_view_top is
begin
  U_CACHE_SYSTEM : entity work.lab8_cache_top
    port map (
      clk_i          => clock_i,
      rst_i          => reset_i,
      cpu_req_i      => cpu_cache_request_i,
      cpu_we_i       => cpu_write_enable_i,
      cpu_addr_i     => cpu_address_tag_set_i,
      cpu_wdata_i    => cpu_write_data_to_cache_i,
      cpu_rdata_o    => cpu_read_data_from_cache_o,
      cpu_ready_o    => cpu_cache_response_ready_o,
      hit_o          => cache_hit_signal_o,
      miss_o         => cache_miss_signal_o,
      ram_req_dbg_o  => memory_request_from_cache_debug_o,
      ram_we_dbg_o   => memory_write_enable_debug_o,
      ram_addr_dbg_o => memory_address_debug_o,
      ram_data_dbg_o => memory_data_debug_o
    );
end architecture;

LABS/student_labs_5_8/lab8_cache/quartus/db/lab8_cache.sim.vcd
$comment
Copyright (C) 1991-2009 Altera Corporation
Your use of Altera Corporation's design tools, logic functions 
and other software and tools, and its AMPP partner logic 
functions, and any output files from any of the foregoing 
(including device programming or simulation files), and any 
associated documentation or information are expressly subject 
to the terms and conditions of the Altera Program License 
Subscription Agreement, Altera MegaCore Function License 
Agreement, or other applicable license agreement, including, 
without limitation, that your use is for the sole purpose of 
programming logic devices manufactured by Altera and sold by 
Altera or its authorized distributors.  Please refer to the 
applicable agreement for further details.
$end

$date 
  05/17/2026 18:02:41 
$end
$version 
 QUARTUS_VCD_EXPORT 1.0 
$end
$timescale
  1 ps
$end
$scope module lab8_cache_rtl_view_top $end
$var reg 1 ! clock_i $end
$var reg 1 " reset_i $end
$var reg 1 # cpu_cache_request_i $end
$var reg 1 $ cpu_write_enable_i $end
$var reg 16 % cpu_address_tag_set_i[15:0] $end
$var reg 16 & cpu_write_data_to_cache_i[15:0] $end
$var reg 16 ' cpu_read_data_from_cache_o[15:0] $end
$var reg 1 ( cpu_cache_response_ready_o $end
$var reg 1 ) cache_hit_signal_o $end
$var reg 1 * cache_miss_signal_o $end
$var reg 1 + memory_request_from_cache_debug_o $end
$var reg 1 , memory_write_enable_debug_o $end
$var reg 16 - memory_address_debug_o[15:0] $end
$var reg 16 . memory_data_debug_o[15:0] $end
$upscope $end
$enddefinitions $end
#0
$dumpvars
0!
1"
0#
0$
b0 %
b0 &
b0 '
0(
0)
0*
0+
0,
b0 -
b0 .
$end
#5000
1!
#10000
0!
#15000
1!
#20000
0!
0"
#25000
1!
#30000
0!
1#
b10000 %
#35000
1!
1*
1+
b10000 -
#40000
0!
#45000
1!
0*
b1000100010000 .
#50000
0!
#55000
1!
#60000
0!
#65000
1!
b1000100010000 '
1(
1*
0+
#70000
0!
0#
#75000
1!
0(
0*
#80000
0!
1#
#85000
1!
1(
1)
#90000
0!
0#
#95000
1!
0(
0)
#100000
0!
#105000
1!
#110000
0!
1#
1$
b1010101111001101 &
#115000
1!
1)
1+
1,
b1010101111001101 .
#120000
0!
#125000
1!
0)
#130000
0!
#135000
1!
1(
0+
0,
#140000
0!
0#
0$
b0 &
#145000
1!
0(
#150000
0!
1#
#155000
1!
b1010101111001101 '
1(
1)
#160000
0!
0#
#165000
1!
0(
0)
#170000
0!
b11000 %
#175000
1!
#180000
0!
1#
#185000
1!
1*
1+
b11000 -
#190000
0!
#195000
1!
0*
b1000110011000 .
#200000
0!
#205000
1!
#210000
0!
#215000
1!
b1000110011000 '
1(
1*
0+
#220000
0!
0#
b10000 %
#225000
1!
0(
0*
#230000
0!
1#
#235000
1!
1*
1+
b10000 -
#240000
0!
#245000
1!
0*
b1010101111001101 .
#250000
0!
#255000
1!
#260000
0!
#265000
1!
b1010101111001101 '
1(
1*
0+
#270000
0!
0#
#275000
1!
0(
0*
