LABS/student_labs_5_8/lab6_stack/src/stack7x16.vhd
library ieee;
use ieee.std_logic_1164.all;
use ieee.numeric_std.all;
use work.lab_variant_pkg.all;

entity stack7x16 is
  port (
    clk_i       : in  std_logic;
    rst_i       : in  std_logic;
    push_i      : in  std_logic;
    pop_i       : in  std_logic;
    din_i       : in  word_t;
    dout_o      : out word_t;
    sp_o        : out unsigned(2 downto 0);
    empty_o     : out std_logic;
    full_o      : out std_logic;
    overflow_o  : out std_logic;
    underflow_o : out std_logic
  );
end entity;

architecture rtl of stack7x16 is
  type stack_mem_t is array (0 to STACK_DEPTH - 1) of word_t;
  signal mem_r       : stack_mem_t := (others => (others => '0'));
  signal sp_r        : unsigned(2 downto 0) := to_unsigned(STACK_DEPTH, 3);
  signal dout_r      : word_t := (others => '0');
  signal overflow_r  : std_logic := '0';
  signal underflow_r : std_logic := '0';
begin
  dout_o      <= dout_r;
  sp_o        <= sp_r;
  empty_o     <= '1' when sp_r = to_unsigned(STACK_DEPTH, 3) else '0';
  full_o      <= '1' when sp_r = to_unsigned(STACK_DEPTH - 1, 3) else '0';
  overflow_o  <= overflow_r;
  underflow_o <= underflow_r;

  process(clk_i)
    variable sp_v : integer;
  begin
    if rising_edge(clk_i) then
      if rst_i = '1' then
        mem_r       <= (others => (others => '0'));
        sp_r        <= to_unsigned(STACK_DEPTH, 3);
        dout_r      <= (others => '0');
        overflow_r  <= '0';
        underflow_r <= '0';
      else
        overflow_r  <= '0';
        underflow_r <= '0';
        sp_v := to_integer(sp_r);

        if push_i = '1' and pop_i = '0' then
          if sp_v = STACK_DEPTH - 1 then
            overflow_r <= '1';
          elsif sp_v = STACK_DEPTH then
            mem_r(0) <= din_i;
            sp_r <= to_unsigned(0, 3);
          else
            mem_r(sp_v + 1) <= din_i;
            sp_r <= to_unsigned(sp_v + 1, 3);
          end if;
        elsif pop_i = '1' and push_i = '0' then
          if sp_v = STACK_DEPTH then
            underflow_r <= '1';
          else
            dout_r <= mem_r(sp_v);
            if sp_v = 0 then
              sp_r <= to_unsigned(STACK_DEPTH, 3);
            else
              sp_r <= to_unsigned(sp_v - 1, 3);
            end if;
          end if;
        end if;
      end if;
    end if;
  end process;
end architecture;

LABS/student_labs_5_8/lab6_stack/src/stack_control.vhd
library ieee;
use ieee.std_logic_1164.all;
use work.lab_variant_pkg.all;

entity stack_control is
  port (
    cmd_i      : in  std_logic_vector(1 downto 0);
    push_o     : out std_logic;
    pop_o      : out std_logic;
    alu_src_o  : out std_logic
  );
end entity;

architecture rtl of stack_control is
begin
  process(cmd_i)
  begin
    push_o    <= '0';
    pop_o     <= '0';
    alu_src_o <= '0';

    case cmd_i is
      when STACK_PUSH_REG =>
        push_o <= '1';
      when STACK_POP_REG =>
        pop_o <= '1';
      when STACK_PUSH_ALU =>
        push_o    <= '1';
        alu_src_o <= '1';
      when others =>
        null;
    end case;
  end process;
end architecture;

LABS/student_labs_5_8/lab6_stack/src/lab6_stack_top.vhd
library ieee;
use ieee.std_logic_1164.all;
use ieee.numeric_std.all;
use work.lab_variant_pkg.all;

entity lab6_stack_top is
  port (
    clk_i       : in  std_logic;
    rst_i       : in  std_logic;
    cmd_i       : in  std_logic_vector(1 downto 0);
    reg_data_i  : in  word_t;
    alu_data_i  : in  word_t;
    stack_out_o : out word_t;
    sp_o        : out unsigned(2 downto 0);
    empty_o     : out std_logic;
    full_o      : out std_logic;
    overflow_o  : out std_logic;
    underflow_o : out std_logic;
    push_dbg_o  : out std_logic;
    pop_dbg_o   : out std_logic
  );
end entity;

architecture structural of lab6_stack_top is
  signal push_s   : std_logic;
  signal pop_s    : std_logic;
  signal alu_src_s: std_logic;
  signal din_s    : word_t;
begin
  U_CTRL : entity work.stack_control
    port map (
      cmd_i     => cmd_i,
      push_o    => push_s,
      pop_o     => pop_s,
      alu_src_o => alu_src_s
    );

  din_s <= alu_data_i when alu_src_s = '1' else reg_data_i;

  U_STACK : entity work.stack7x16
    port map (
      clk_i       => clk_i,
      rst_i       => rst_i,
      push_i      => push_s,
      pop_i       => pop_s,
      din_i       => din_s,
      dout_o      => stack_out_o,
      sp_o        => sp_o,
      empty_o     => empty_o,
      full_o      => full_o,
      overflow_o  => overflow_o,
      underflow_o => underflow_o
    );

  push_dbg_o <= push_s;
  pop_dbg_o  <= pop_s;
end architecture;

LABS/student_labs_5_8/lab6_stack/tb/tb_lab6_stack.vhd
library ieee;
use ieee.std_logic_1164.all;
use ieee.numeric_std.all;
use work.lab_variant_pkg.all;

entity tb_lab6_stack is
end entity;

architecture sim of tb_lab6_stack is
  signal clk       : std_logic := '0';
  signal rst       : std_logic := '1';
  signal cmd       : std_logic_vector(1 downto 0) := STACK_IDLE;
  signal reg_data  : word_t := (others => '0');
  signal alu_data  : word_t := (others => '0');
  signal stack_out : word_t;
  signal sp        : unsigned(2 downto 0);
  signal empty     : std_logic;
  signal full      : std_logic;
  signal overflow  : std_logic;
  signal underflow : std_logic;
  signal push_dbg  : std_logic;
  signal pop_dbg   : std_logic;

  procedure one_cycle(signal clk_s : in std_logic) is
  begin
    wait until rising_edge(clk_s);
    wait for 1 ns;
  end procedure;
begin
  clk <= not clk after 5 ns;

  DUT : entity work.lab6_stack_top
    port map (
      clk_i       => clk,
      rst_i       => rst,
      cmd_i       => cmd,
      reg_data_i  => reg_data,
      alu_data_i  => alu_data,
      stack_out_o => stack_out,
      sp_o        => sp,
      empty_o     => empty,
      full_o      => full,
      overflow_o  => overflow,
      underflow_o => underflow,
      push_dbg_o  => push_dbg,
      pop_dbg_o   => pop_dbg
    );

  stimulus : process
  begin
    one_cycle(clk);
    rst <= '0';
    one_cycle(clk);
    assert sp = to_unsigned(7, 3) and empty = '1' and full = '0'
      report "Reset state must be empty stack with SP=7" severity failure;

    reg_data <= x"1111";
    cmd <= STACK_PUSH_REG;
    one_cycle(clk);
    cmd <= STACK_IDLE;
    assert sp = to_unsigned(0, 3)
      report "SP must point to first occupied cell after first push" severity failure;

    reg_data <= x"2222";
    cmd <= STACK_PUSH_REG;
    one_cycle(clk);
    cmd <= STACK_IDLE;

    cmd <= STACK_POP_REG;
    one_cycle(clk);
    cmd <= STACK_IDLE;
    assert stack_out = x"2222" and sp = to_unsigned(0, 3)
      report "POP must return the last pushed register value" severity failure;

    alu_data <= x"000F";
    cmd <= STACK_PUSH_ALU;
    one_cycle(clk);
    cmd <= STACK_IDLE;
    assert sp = to_unsigned(1, 3)
      report "ALU result push must occupy stack cell" severity failure;

    reg_data <= x"3333"; cmd <= STACK_PUSH_REG; one_cycle(clk);
    reg_data <= x"4444"; cmd <= STACK_PUSH_REG; one_cycle(clk);
    reg_data <= x"5555"; cmd <= STACK_PUSH_REG; one_cycle(clk);
    reg_data <= x"6666"; cmd <= STACK_PUSH_REG; one_cycle(clk);
    reg_data <= x"7777"; cmd <= STACK_PUSH_REG; one_cycle(clk);
    cmd <= STACK_IDLE;
    assert full = '1' and sp = to_unsigned(6, 3)
      report "Seven occupied words must set FULL" severity failure;

    reg_data <= x"8888";
    cmd <= STACK_PUSH_REG;
    one_cycle(clk);
    cmd <= STACK_IDLE;
    assert overflow = '1'
      report "Push into full stack must set overflow flag" severity failure;

    cmd <= STACK_POP_REG; one_cycle(clk);
    cmd <= STACK_POP_REG; one_cycle(clk);
    cmd <= STACK_POP_REG; one_cycle(clk);
    cmd <= STACK_POP_REG; one_cycle(clk);
    cmd <= STACK_POP_REG; one_cycle(clk);
    cmd <= STACK_POP_REG; one_cycle(clk);
    cmd <= STACK_POP_REG; one_cycle(clk);
    cmd <= STACK_IDLE;
    assert empty = '1' and sp = to_unsigned(7, 3)
      report "After seven pops stack must be empty" severity failure;

    cmd <= STACK_POP_REG;
    one_cycle(clk);
    cmd <= STACK_IDLE;
    assert underflow = '1'
      report "Pop from empty stack must set underflow flag" severity failure;

    assert false report "tb_lab6_stack: TEST PASSED" severity note;
    wait;
  end process;
end architecture;

LABS/student_labs_5_8/sim/vcd/lab6_stack.vcd
$date
  Sun May 17 14:14:03 2026
$end
$version
  GHDL v0
$end
$timescale
  1 fs
$end
$scope module standard $end
$upscope $end
$scope module textio $end
$upscope $end
$scope module std_logic_1164 $end
$upscope $end
$scope module numeric_std $end
$upscope $end
$scope module lab_variant_pkg $end
$upscope $end
$scope module tb_lab6_stack $end
$var reg 1 ! clk $end
$var reg 1 " rst $end
$var reg 2 # cmd[1:0] $end
$var reg 16 $ reg_data[15:0] $end
$var reg 16 % alu_data[15:0] $end
$var reg 16 & stack_out[15:0] $end
$var reg 3 ' sp[2:0] $end
$var reg 1 ( empty $end
$var reg 1 ) full $end
$var reg 1 * overflow $end
$var reg 1 + underflow $end
$var reg 1 , push_dbg $end
$var reg 1 - pop_dbg $end
$scope module dut $end
$var reg 1 . clk_i $end
$var reg 1 / rst_i $end
$var reg 2 0 cmd_i[1:0] $end
$var reg 16 1 reg_data_i[15:0] $end
$var reg 16 2 alu_data_i[15:0] $end
$var reg 16 3 stack_out_o[15:0] $end
$var reg 3 4 sp_o[2:0] $end
$var reg 1 5 empty_o $end
$var reg 1 6 full_o $end
$var reg 1 7 overflow_o $end
$var reg 1 8 underflow_o $end
$var reg 1 9 push_dbg_o $end
$var reg 1 : pop_dbg_o $end
$var reg 1 ; push_s $end
$var reg 1 < pop_s $end
$var reg 1 = alu_src_s $end
$var reg 16 > din_s[15:0] $end
$scope module u_ctrl $end
$var reg 2 ? cmd_i[1:0] $end
$var reg 1 @ push_o $end
$var reg 1 A pop_o $end
$var reg 1 B alu_src_o $end
$upscope $end
$scope module u_stack $end
$var reg 1 C clk_i $end
$var reg 1 D rst_i $end
$var reg 1 E push_i $end
$var reg 1 F pop_i $end
$var reg 16 G din_i[15:0] $end
$var reg 16 H dout_o[15:0] $end
$var reg 3 I sp_o[2:0] $end
$var reg 1 J empty_o $end
$var reg 1 K full_o $end
$var reg 1 L overflow_o $end
$var reg 1 M underflow_o $end
$comment mem_r is not handled $end
$var reg 3 N sp_r[2:0] $end
$var reg 16 O dout_r[15:0] $end
$var reg 1 P overflow_r $end
$var reg 1 Q underflow_r $end
$upscope $end
$upscope $end
$upscope $end
$enddefinitions $end
#0
0!
1"
b00 #
b0000000000000000 $
b0000000000000000 %
b0000000000000000 &
b111 '
1(
0)
0*
0+
0,
0-
0.
1/
b00 0
b0000000000000000 1
b0000000000000000 2
b0000000000000000 3
b111 4
15
06
07
08
09
0:
0;
0<
0=
b0000000000000000 >
b00 ?
0@
0A
0B
0C
1D
0E
0F
b0000000000000000 G
b0000000000000000 H
b111 I
1J
0K
0L
0M
b111 N
b0000000000000000 O
0P
0Q
#5000000
1!
1.
1C
#6000000
0"
0/
0D
#10000000
0!
0.
0C
#15000000
1!
1.
1C
#16000000
b01 #
b0001000100010001 $
1,
b01 0
b0001000100010001 1
19
1;
b0001000100010001 >
b01 ?
1@
1E
b0001000100010001 G
#20000000
0!
0.
0C
#25000000
1!
b000 '
0(
1.
b000 4
05
1C
b000 I
0J
b000 N
#26000000
b0010001000100010 $
b0010001000100010 1
b0010001000100010 >
b0010001000100010 G
#30000000
0!
0.
0C
#35000000
1!
b001 '
1.
b001 4
1C
b001 I
b001 N
#36000000
b10 #
0,
1-
b10 0
09
1:
0;
1<
b10 ?
0@
1A
0E
1F
#40000000
0!
0.
0C
#45000000
1!
b0010001000100010 &
b000 '
1.
b0010001000100010 3
b000 4
1C
b0010001000100010 H
b000 I
b000 N
b0010001000100010 O
#46000000
b11 #
b0000000000001111 %
1,
0-
b11 0
b0000000000001111 2
19
0:
1;
0<
1=
b0000000000001111 >
b11 ?
1@
0A
1B
1E
0F
b0000000000001111 G
#50000000
0!
0.
0C
#55000000
1!
b001 '
1.
b001 4
1C
b001 I
b001 N
#56000000
b01 #
b0011001100110011 $
b01 0
b0011001100110011 1
0=
b0011001100110011 >
b01 ?
1@
0B
b0011001100110011 G
#60000000
0!
0.
0C
#65000000
1!
b010 '
1.
b010 4
1C
b010 I
b010 N
#66000000
b0100010001000100 $
b0100010001000100 1
b0100010001000100 >
b0100010001000100 G
#70000000
0!
0.
0C
#75000000
1!
b011 '
1.
b011 4
1C
b011 I
b011 N
#76000000
b0101010101010101 $
b0101010101010101 1
b0101010101010101 >
b0101010101010101 G
#80000000
0!
0.
0C
#85000000
1!
b100 '
1.
b100 4
1C
b100 I
b100 N
#86000000
b0110011001100110 $
b0110011001100110 1
b0110011001100110 >
b0110011001100110 G
#90000000
0!
0.
0C
#95000000
1!
b101 '
1.
b101 4
1C
b101 I
b101 N
#96000000
b0111011101110111 $
b0111011101110111 1
b0111011101110111 >
b0111011101110111 G
#100000000
0!
0.
0C
#105000000
1!
b110 '
1)
1.
b110 4
16
1C
b110 I
1K
b110 N
#106000000
b1000100010001000 $
b1000100010001000 1
b1000100010001000 >
b1000100010001000 G
#110000000
0!
0.
0C
#115000000
1!
1*
1.
17
1C
1L
1P
#116000000
b10 #
0,
1-
b10 0
09
1:
0;
1<
b10 ?
0@
1A
0E
1F
#120000000
0!
0.
0C
#125000000
1!
b0111011101110111 &
b101 '
0)
0*
1.
b0111011101110111 3
b101 4
06
07
1C
b0111011101110111 H
b101 I
0K
0L
b101 N
b0111011101110111 O
0P
#130000000
0!
0.
0C
#135000000
1!
b0110011001100110 &
b100 '
1.
b0110011001100110 3
b100 4
1C
b0110011001100110 H
b100 I
b100 N
b0110011001100110 O
#140000000
0!
0.
0C
#145000000
1!
b0101010101010101 &
b011 '
1.
b0101010101010101 3
b011 4
1C
b0101010101010101 H
b011 I
b011 N
b0101010101010101 O
#150000000
0!
0.
0C
#155000000
1!
b0100010001000100 &
b010 '
1.
b0100010001000100 3
b010 4
1C
b0100010001000100 H
b010 I
b010 N
b0100010001000100 O
#160000000
0!
0.
0C
#165000000
1!
b0011001100110011 &
b001 '
1.
b0011001100110011 3
b001 4
1C
b0011001100110011 H
b001 I
b001 N
b0011001100110011 O
#170000000
0!
0.
0C
#175000000
1!
b0000000000001111 &
b000 '
1.
b0000000000001111 3
b000 4
1C
b0000000000001111 H
b000 I
b000 N
b0000000000001111 O
#180000000
0!
0.
0C
#185000000
1!
b0001000100010001 &
b111 '
1(
1.
b0001000100010001 3
b111 4
15
1C
b0001000100010001 H
b111 I
1J
b111 N
b0001000100010001 O
#190000000
0!
0.
0C
#195000000
1!
1+
1.
18
1C
1M
1Q
#196000000
b00 #
0-
b00 0
0:
0<
b00 ?
0A
0F
#200000000
0!
0.
0C
#205000000
1!
0+
1.
08
1C
0M
0Q
