LABS/student_labs_5_8/lab7_bus_arbiter/src/slave_sync.vhd
library ieee;
use ieee.std_logic_1164.all;
use work.lab_variant_pkg.all;

entity slave_sync is
  port (
    clk_i    : in  std_logic;
    rst_i    : in  std_logic;
    strobe_i : in  std_logic;
    data_i   : in  word_t;
    data_o   : out word_t;
    valid_o  : out std_logic
  );
end entity;

architecture rtl of slave_sync is
  signal data_r  : word_t := (others => '0');
  signal valid_r : std_logic := '0';
begin
  process(clk_i)
  begin
    if rising_edge(clk_i) then
      if rst_i = '1' then
        data_r  <= (others => '0');
        valid_r <= '0';
      else
        valid_r <= strobe_i;
        if strobe_i = '1' then
          data_r <= data_i;
        end if;
      end if;
    end if;
  end process;

  data_o  <= data_r;
  valid_o <= valid_r;
end architecture;

LABS/student_labs_5_8/lab7_bus_arbiter/src/bus_mux_4.vhd
library ieee;
use ieee.std_logic_1164.all;
use work.lab_variant_pkg.all;

entity bus_mux_4 is
  port (
    grant_i : in  std_logic_vector(3 downto 0);
    data0_i : in  word_t;
    data1_i : in  word_t;
    data2_i : in  word_t;
    data3_i : in  word_t;
    bus_o   : out word_t
  );
end entity;

architecture rtl of bus_mux_4 is
begin
  process(grant_i, data0_i, data1_i, data2_i, data3_i)
  begin
    bus_o <= (others => '0');
    if grant_i(0) = '1' then
      bus_o <= data0_i;
    elsif grant_i(1) = '1' then
      bus_o <= data1_i;
    elsif grant_i(2) = '1' then
      bus_o <= data2_i;
    elsif grant_i(3) = '1' then
      bus_o <= data3_i;
    end if;
  end process;
end architecture;

LABS/student_labs_5_8/lab7_bus_arbiter/src/bus_arbiter_parallel_quantum.vhd
library ieee;
use ieee.std_logic_1164.all;
use ieee.numeric_std.all;

entity bus_arbiter_parallel_quantum is
  generic (
    QUANTUM_CYCLES : positive := 2
  );
  port (
    clk_i          : in  std_logic;
    rst_i          : in  std_logic;
    req_i          : in  std_logic_vector(3 downto 0);
    grant_o        : out std_logic_vector(3 downto 0);
    slot_o         : out unsigned(1 downto 0);
    quantum_tick_o : out std_logic;
    busy_o         : out std_logic
  );
end entity;

architecture rtl of bus_arbiter_parallel_quantum is
  signal slot_r     : unsigned(1 downto 0) := (others => '0');
  signal quantum_r  : integer range 0 to QUANTUM_CYCLES - 1 := 0;
  signal grant_s    : std_logic_vector(3 downto 0);
  signal tick_s     : std_logic;
begin
  process(req_i, slot_r)
  begin
    grant_s <= (others => '0');
    if req_i(to_integer(slot_r)) = '1' then
      grant_s(to_integer(slot_r)) <= '1';
    end if;
  end process;

  process(clk_i)
  begin
    if rising_edge(clk_i) then
      if rst_i = '1' then
        slot_r    <= (others => '0');
        quantum_r <= 0;
      elsif quantum_r = QUANTUM_CYCLES - 1 then
        quantum_r <= 0;
        slot_r    <= slot_r + 1;
      else
        quantum_r <= quantum_r + 1;
      end if;
    end if;
  end process;

  tick_s <= '1' when quantum_r = QUANTUM_CYCLES - 1 else '0';

  grant_o        <= grant_s;
  slot_o         <= slot_r;
  quantum_tick_o <= tick_s;
  busy_o         <= '1' when grant_s /= "0000" else '0';
end architecture;

LABS/student_labs_5_8/lab7_bus_arbiter/src/master_device.vhd
library ieee;
use ieee.std_logic_1164.all;
use ieee.numeric_std.all;
use work.lab_variant_pkg.all;

entity master_device is
  generic (
    ID_VALUE    : natural := 1;
    START_CYCLE : natural := 1;
    HOLD_CYCLES : natural := 8
  );
  port (
    clk_i   : in  std_logic;
    rst_i   : in  std_logic;
    grant_i : in  std_logic;
    req_o   : out std_logic;
    data_o  : out word_t;
    used_o  : out std_logic
  );
end entity;

architecture rtl of master_device is
  signal cycle_r : natural range 0 to 255 := 0;
  signal req_s   : std_logic;
  signal used_r  : std_logic := '0';
begin
  req_s <= '1' when cycle_r >= START_CYCLE and cycle_r < START_CYCLE + HOLD_CYCLES else '0';

  process(clk_i)
  begin
    if rising_edge(clk_i) then
      if rst_i = '1' then
        cycle_r <= 0;
        used_r  <= '0';
      else
        if cycle_r < 255 then
          cycle_r <= cycle_r + 1;
        end if;
        if grant_i = '1' then
          used_r <= '1';
        end if;
      end if;
    end if;
  end process;

  req_o  <= req_s;
  data_o <= std_logic_vector(to_unsigned(ID_VALUE, DATA_W));
  used_o <= used_r;
end architecture;

LABS/student_labs_5_8/lab7_bus_arbiter/src/lab7_bus_top.vhd
library ieee;
use ieee.std_logic_1164.all;
use ieee.numeric_std.all;
use work.lab_variant_pkg.all;

entity lab7_bus_top is
  port (
    clk_i       : in  std_logic;
    rst_i       : in  std_logic;
    req_o       : out std_logic_vector(3 downto 0);
    grant_o     : out std_logic_vector(3 downto 0);
    bus_data_o  : out word_t;
    slave_data_o: out word_t;
    slave_valid_o: out std_logic;
    slot_o      : out unsigned(1 downto 0);
    used_o      : out std_logic_vector(3 downto 0)
  );
end entity;

architecture structural of lab7_bus_top is
  signal req_s        : std_logic_vector(3 downto 0);
  signal grant_s      : std_logic_vector(3 downto 0);
  signal data0_s      : word_t;
  signal data1_s      : word_t;
  signal data2_s      : word_t;
  signal data3_s      : word_t;
  signal bus_s        : word_t;
  signal busy_s       : std_logic;
  signal tick_s       : std_logic;
begin
  U_MASTER0 : entity work.master_device
    generic map (ID_VALUE => 16#1111#, START_CYCLE => 1, HOLD_CYCLES => 10)
    port map (clk_i => clk_i, rst_i => rst_i, grant_i => grant_s(0), req_o => req_s(0), data_o => data0_s, used_o => used_o(0));

  U_MASTER1 : entity work.master_device
    generic map (ID_VALUE => 16#2222#, START_CYCLE => 2, HOLD_CYCLES => 10)
    port map (clk_i => clk_i, rst_i => rst_i, grant_i => grant_s(1), req_o => req_s(1), data_o => data1_s, used_o => used_o(1));

  U_MASTER2 : entity work.master_device
    generic map (ID_VALUE => 16#3333#, START_CYCLE => 4, HOLD_CYCLES => 10)
    port map (clk_i => clk_i, rst_i => rst_i, grant_i => grant_s(2), req_o => req_s(2), data_o => data2_s, used_o => used_o(2));

  U_MASTER3 : entity work.master_device
    generic map (ID_VALUE => 16#4444#, START_CYCLE => 6, HOLD_CYCLES => 10)
    port map (clk_i => clk_i, rst_i => rst_i, grant_i => grant_s(3), req_o => req_s(3), data_o => data3_s, used_o => used_o(3));

  U_ARBITER : entity work.bus_arbiter_parallel_quantum
    generic map (QUANTUM_CYCLES => 2)
    port map (
      clk_i          => clk_i,
      rst_i          => rst_i,
      req_i          => req_s,
      grant_o        => grant_s,
      slot_o         => slot_o,
      quantum_tick_o => tick_s,
      busy_o         => busy_s
    );

  U_BUS : entity work.bus_mux_4
    port map (
      grant_i => grant_s,
      data0_i => data0_s,
      data1_i => data1_s,
      data2_i => data2_s,
      data3_i => data3_s,
      bus_o   => bus_s
    );

  U_SLAVE : entity work.slave_sync
    port map (
      clk_i    => clk_i,
      rst_i    => rst_i,
      strobe_i => busy_s,
      data_i   => bus_s,
      data_o   => slave_data_o,
      valid_o  => slave_valid_o
    );

  req_o      <= req_s;
  grant_o    <= grant_s;
  bus_data_o <= bus_s;
end architecture;

LABS/student_labs_5_8/lab7_bus_arbiter/tb/tb_lab7_bus.vhd
library ieee;
use ieee.std_logic_1164.all;
use ieee.numeric_std.all;
use work.lab_variant_pkg.all;

entity tb_lab7_bus is
end entity;

architecture sim of tb_lab7_bus is
  signal clk         : std_logic := '0';
  signal rst         : std_logic := '1';
  signal req         : std_logic_vector(3 downto 0);
  signal grant       : std_logic_vector(3 downto 0);
  signal bus_data    : word_t;
  signal slave_data  : word_t;
  signal slave_valid : std_logic;
  signal slot        : unsigned(1 downto 0);
  signal used        : std_logic_vector(3 downto 0);

  function one_hot_or_zero(v : std_logic_vector(3 downto 0)) return boolean is
    variable cnt : integer := 0;
  begin
    for i in 0 to 3 loop
      if v(i) = '1' then
        cnt := cnt + 1;
      end if;
    end loop;
    return cnt <= 1;
  end function;
begin
  clk <= not clk after 5 ns;

  DUT : entity work.lab7_bus_top
    port map (
      clk_i         => clk,
      rst_i         => rst,
      req_o         => req,
      grant_o       => grant,
      bus_data_o    => bus_data,
      slave_data_o  => slave_data,
      slave_valid_o => slave_valid,
      slot_o        => slot,
      used_o        => used
    );

  stimulus : process
    variable seen : std_logic_vector(3 downto 0) := (others => '0');
  begin
    wait until rising_edge(clk);
    wait until rising_edge(clk);
    rst <= '0';

    for cycle in 0 to 24 loop
      wait until rising_edge(clk);
      wait for 1 ns;
      assert one_hot_or_zero(grant)
        report "Central arbiter must never grant the bus to more than one master" severity failure;

      for i in 0 to 3 loop
        if grant(i) = '1' then
          seen(i) := '1';
          assert req(i) = '1'
            report "Grant may be asserted only for an active request" severity failure;
        end if;
      end loop;
    end loop;

    assert seen = "1111"
      report "Every master must receive the bus during the modeled interval" severity failure;
    assert used = "1111"
      report "Each master must remember at least one successful grant" severity failure;
    assert slave_valid = '0' or slave_data = x"1111" or slave_data = x"2222" or slave_data = x"3333" or slave_data = x"4444"
      report "Slave must latch one of the master data words" severity failure;

    assert false report "tb_lab7_bus: TEST PASSED" severity note;
    wait;
  end process;
end architecture;

LABS/student_labs_5_8/sim/vcd/lab7_bus_arbiter.vcd
$date
  Thu May 14 23:23:55 2026
$end
$version
  GHDL v0
$end
$timescale
  1 fs
$end
$scope module standard $end
$upscope $end
$scope module textio $end
$upscope $end
$scope module std_logic_1164 $end
$upscope $end
$scope module numeric_std $end
$upscope $end
$scope module lab_variant_pkg $end
$upscope $end
$scope module tb_lab7_bus $end
$var reg 1 ! clk $end
$var reg 1 " rst $end
$var reg 4 # req[3:0] $end
$var reg 4 $ grant[3:0] $end
$var reg 16 % bus_data[15:0] $end
$var reg 16 & slave_data[15:0] $end
$var reg 1 ' slave_valid $end
$var reg 2 ( slot[1:0] $end
$var reg 4 ) used[3:0] $end
$scope module dut $end
$var reg 1 * clk_i $end
$var reg 1 + rst_i $end
$var reg 4 , req_o[3:0] $end
$var reg 4 - grant_o[3:0] $end
$var reg 16 . bus_data_o[15:0] $end
$var reg 16 / slave_data_o[15:0] $end
$var reg 1 0 slave_valid_o $end
$var reg 2 1 slot_o[1:0] $end
$var reg 4 2 used_o[3:0] $end
$var reg 4 3 req_s[3:0] $end
$var reg 4 4 grant_s[3:0] $end
$var reg 16 5 data0_s[15:0] $end
$var reg 16 6 data1_s[15:0] $end
$var reg 16 7 data2_s[15:0] $end
$var reg 16 8 data3_s[15:0] $end
$var reg 16 9 bus_s[15:0] $end
$var reg 1 : busy_s $end
$var reg 1 ; tick_s $end
$scope module u_master0 $end
$var reg 1 < clk_i $end
$var reg 1 = rst_i $end
$var reg 1 > grant_i $end
$var reg 1 ? req_o $end
$var reg 16 @ data_o[15:0] $end
$var reg 1 A used_o $end
$var integer 32 B cycle_r $end
$var reg 1 C req_s $end
$var reg 1 D used_r $end
$upscope $end
$scope module u_master1 $end
$var reg 1 E clk_i $end
$var reg 1 F rst_i $end
$var reg 1 G grant_i $end
$var reg 1 H req_o $end
$var reg 16 I data_o[15:0] $end
$var reg 1 J used_o $end
$var integer 32 K cycle_r $end
$var reg 1 L req_s $end
$var reg 1 M used_r $end
$upscope $end
$scope module u_master2 $end
$var reg 1 N clk_i $end
$var reg 1 O rst_i $end
$var reg 1 P grant_i $end
$var reg 1 Q req_o $end
$var reg 16 R data_o[15:0] $end
$var reg 1 S used_o $end
$var integer 32 T cycle_r $end
$var reg 1 U req_s $end
$var reg 1 V used_r $end
$upscope $end
$scope module u_master3 $end
$var reg 1 W clk_i $end
$var reg 1 X rst_i $end
$var reg 1 Y grant_i $end
$var reg 1 Z req_o $end
$var reg 16 [ data_o[15:0] $end
$var reg 1 \ used_o $end
$var integer 32 ] cycle_r $end
$var reg 1 ^ req_s $end
$var reg 1 _ used_r $end
$upscope $end
$scope module u_arbiter $end
$var reg 1 ` clk_i $end
$var reg 1 a rst_i $end
$var reg 4 b req_i[3:0] $end
$var reg 4 c grant_o[3:0] $end
$var reg 2 d slot_o[1:0] $end
$var reg 1 e quantum_tick_o $end
$var reg 1 f busy_o $end
$var reg 2 g slot_r[1:0] $end
$var integer 32 h quantum_r $end
$var reg 4 i grant_s[3:0] $end
$var reg 1 j tick_s $end
$upscope $end
$scope module u_bus $end
$var reg 4 k grant_i[3:0] $end
$var reg 16 l data0_i[15:0] $end
$var reg 16 m data1_i[15:0] $end
$var reg 16 n data2_i[15:0] $end
$var reg 16 o data3_i[15:0] $end
$var reg 16 p bus_o[15:0] $end
$upscope $end
$scope module u_slave $end
$var reg 1 q clk_i $end
$var reg 1 r rst_i $end
$var reg 1 s strobe_i $end
$var reg 16 t data_i[15:0] $end
$var reg 16 u data_o[15:0] $end
$var reg 1 v valid_o $end
$var reg 16 w data_r[15:0] $end
$var reg 1 x valid_r $end
$upscope $end
$upscope $end
$upscope $end
$enddefinitions $end
#0
0!
1"
b0000 #
b0000 $
b0000000000000000 %
b0000000000000000 &
0'
b00 (
b0000 )
0*
1+
b0000 ,
b0000 -
b0000000000000000 .
b0000000000000000 /
00
b00 1
b0000 2
b0000 3
b0000 4
b0001000100010001 5
b0010001000100010 6
b0011001100110011 7
b0100010001000100 8
b0000000000000000 9
0:
0;
0<
1=
0>
0?
b0001000100010001 @
0A
b0 B
0C
0D
0E
1F
0G
0H
b0010001000100010 I
0J
b0 K
0L
0M
0N
1O
0P
0Q
b0011001100110011 R
0S
b0 T
0U
0V
0W
1X
0Y
0Z
b0100010001000100 [
0\
b0 ]
0^
0_
0`
1a
b0000 b
b0000 c
b00 d
0e
0f
b00 g
b0 h
b0000 i
0j
b0000 k
b0001000100010001 l
b0010001000100010 m
b0011001100110011 n
b0100010001000100 o
b0000000000000000 p
0q
1r
0s
b0000000000000000 t
b0000000000000000 u
0v
b0000000000000000 w
0x
#5000000
1!
1*
1<
1E
1N
1W
1`
1q
#10000000
0!
0*
0<
0E
0N
0W
0`
0q
#15000000
1!
0"
1*
0+
1<
0=
1E
0F
1N
0O
1W
0X
1`
0a
1q
0r
#20000000
0!
0*
0<
0E
0N
0W
0`
0q
#25000000
1!
b0001 #
b0001 $
b0001000100010001 %
1*
b0001 ,
b0001 -
b0001000100010001 .
b0001 3
b0001 4
b0001000100010001 9
1:
1;
1<
1>
1?
b1 B
1C
1E
b1 K
1N
b1 T
1W
b1 ]
1`
b0001 b
b0001 c
1e
1f
b1 h
b0001 i
1j
b0001 k
b0001000100010001 p
1q
1s
b0001000100010001 t
#30000000
0!
0*
0<
0E
0N
0W
0`
0q
#35000000
1!
b0011 #
b0010 $
b0010001000100010 %
b0001000100010001 &
1'
b01 (
b0001 )
1*
b0011 ,
b0010 -
b0010001000100010 .
b0001000100010001 /
10
b01 1
b0001 2
b0011 3
b0010 4
b0010001000100010 9
1:
0;
1<
0>
1A
b10 B
1D
1E
1G
1H
b10 K
1L
1N
b10 T
1W
b10 ]
1`
b0011 b
b0010 c
b01 d
0e
1f
b01 g
b0 h
b0010 i
0j
b0010 k
b0010001000100010 p
1q
1s
b0010001000100010 t
b0001000100010001 u
1v
b0001000100010001 w
1x
#40000000
0!
0*
0<
0E
0N
0W
0`
0q
#45000000
1!
b0010001000100010 &
b0011 )
1*
b0010001000100010 /
b0011 2
1;
1<
b11 B
1E
1J
b11 K
1M
1N
b11 T
1W
b11 ]
1`
1e
b1 h
1j
1q
b0010001000100010 u
b0010001000100010 w
#50000000
0!
0*
0<
0E
0N
0W
0`
0q
#55000000
1!
b0111 #
b0100 $
b0011001100110011 %
b10 (
1*
b0111 ,
b0100 -
b0011001100110011 .
b10 1
b0111 3
b0100 4
b0011001100110011 9
1:
0;
1<
b100 B
1E
0G
b100 K
1N
1P
1Q
b100 T
1U
1W
b100 ]
1`
b0111 b
b0100 c
b10 d
0e
1f
b10 g
b0 h
b0100 i
0j
b0100 k
b0011001100110011 p
1q
1s
b0011001100110011 t
#60000000
0!
0*
0<
0E
0N
0W
0`
0q
#65000000
1!
b0011001100110011 &
b0111 )
1*
b0011001100110011 /
b0111 2
1;
1<
b101 B
1E
b101 K
1N
1S
b101 T
1V
1W
b101 ]
1`
1e
b1 h
1j
1q
b0011001100110011 u
b0011001100110011 w
#70000000
0!
0*
0<
0E
0N
0W
0`
0q
#75000000
1!
b1111 #
b1000 $
b0100010001000100 %
b11 (
1*
b1111 ,
b1000 -
b0100010001000100 .
b11 1
b1111 3
b1000 4
b0100010001000100 9
1:
0;
1<
b110 B
1E
b110 K
1N
0P
b110 T
1W
1Y
1Z
b110 ]
1^
1`
b1111 b
b1000 c
b11 d
0e
1f
b11 g
b0 h
b1000 i
0j
b1000 k
b0100010001000100 p
1q
1s
b0100010001000100 t
#80000000
0!
0*
0<
0E
0N
0W
0`
0q
#85000000
1!
b0100010001000100 &
b1111 )
1*
b0100010001000100 /
b1111 2
1;
1<
b111 B
1E
b111 K
1N
b111 T
1W
1\
b111 ]
1_
1`
1e
b1 h
1j
1q
b0100010001000100 u
b0100010001000100 w
#90000000
0!
0*
0<
0E
0N
0W
0`
0q
#95000000
1!
b0001 $
b0001000100010001 %
b00 (
1*
b0001 -
b0001000100010001 .
b00 1
b0001 4
b0001000100010001 9
0;
1<
1>
b1000 B
1E
b1000 K
1N
b1000 T
1W
0Y
b1000 ]
1`
b0001 c
b00 d
0e
b00 g
b0 h
b0001 i
0j
b0001 k
b0001000100010001 p
1q
b0001000100010001 t
#100000000
0!
0*
0<
0E
0N
0W
0`
0q
#105000000
1!
b0001000100010001 &
1*
b0001000100010001 /
1;
1<
b1001 B
1E
b1001 K
1N
b1001 T
1W
b1001 ]
1`
1e
b1 h
1j
1q
b0001000100010001 u
b0001000100010001 w
#110000000
0!
0*
0<
0E
0N
0W
0`
0q
#115000000
1!
b0010 $
b0010001000100010 %
b01 (
1*
b0010 -
b0010001000100010 .
b01 1
b0010 4
b0010001000100010 9
0;
1<
0>
b1010 B
1E
1G
b1010 K
1N
b1010 T
1W
b1010 ]
1`
b0010 c
b01 d
0e
b01 g
b0 h
b0010 i
0j
b0010 k
b0010001000100010 p
1q
b0010001000100010 t
#120000000
0!
0*
0<
0E
0N
0W
0`
0q
#125000000
1!
b1110 #
b0010001000100010 &
1*
b1110 ,
b0010001000100010 /
b1110 3
1;
1<
0?
b1011 B
0C
1E
b1011 K
1N
b1011 T
1W
b1011 ]
1`
b1110 b
1e
b1 h
1j
1q
b0010001000100010 u
b0010001000100010 w
#130000000
0!
0*
0<
0E
0N
0W
0`
0q
#135000000
1!
b1100 #
b0100 $
b0011001100110011 %
b10 (
1*
b1100 ,
b0100 -
b0011001100110011 .
b10 1
b1100 3
b0100 4
b0011001100110011 9
0;
1<
b1100 B
1E
0G
0H
b1100 K
0L
1N
1P
b1100 T
1W
b1100 ]
1`
b1100 b
b0100 c
b10 d
0e
b10 g
b0 h
b0100 i
0j
b0100 k
b0011001100110011 p
1q
b0011001100110011 t
#140000000
0!
0*
0<
0E
0N
0W
0`
0q
#145000000
1!
b0011001100110011 &
1*
b0011001100110011 /
1;
1<
b1101 B
1E
b1101 K
1N
b1101 T
1W
b1101 ]
1`
1e
b1 h
1j
1q
b0011001100110011 u
b0011001100110011 w
#150000000
0!
0*
0<
0E
0N
0W
0`
0q
#155000000
1!
b1000 #
b1000 $
b0100010001000100 %
b11 (
1*
b1000 ,
b1000 -
b0100010001000100 .
b11 1
b1000 3
b1000 4
b0100010001000100 9
0;
1<
b1110 B
1E
b1110 K
1N
0P
0Q
b1110 T
0U
1W
1Y
b1110 ]
1`
b1000 b
b1000 c
b11 d
0e
b11 g
b0 h
b1000 i
0j
b1000 k
b0100010001000100 p
1q
b0100010001000100 t
#160000000
0!
0*
0<
0E
0N
0W
0`
0q
#165000000
1!
b0100010001000100 &
1*
b0100010001000100 /
1;
1<
b1111 B
1E
b1111 K
1N
b1111 T
1W
b1111 ]
1`
1e
b1 h
1j
1q
b0100010001000100 u
b0100010001000100 w
#170000000
0!
0*
0<
0E
0N
0W
0`
0q
#175000000
1!
b0000 #
b0000 $
b0000000000000000 %
b00 (
1*
b0000 ,
b0000 -
b0000000000000000 .
b00 1
b0000 3
b0000 4
b0000000000000000 9
0:
0;
1<
b10000 B
1E
b10000 K
1N
b10000 T
1W
0Y
0Z
b10000 ]
0^
1`
b0000 b
b0000 c
b00 d
0e
0f
b00 g
b0 h
b0000 i
0j
b0000 k
b0000000000000000 p
1q
0s
b0000000000000000 t
#180000000
0!
0*
0<
0E
0N
0W
0`
0q
#185000000
1!
0'
1*
00
1;
1<
b10001 B
1E
b10001 K
1N
b10001 T
1W
b10001 ]
1`
1e
b1 h
1j
1q
0v
0x
#190000000
0!
0*
0<
0E
0N
0W
0`
0q
#195000000
1!
b01 (
1*
b01 1
0;
1<
b10010 B
1E
b10010 K
1N
b10010 T
1W
b10010 ]
1`
b01 d
0e
b01 g
b0 h
0j
1q
#200000000
0!
0*
0<
0E
0N
0W
0`
0q
#205000000
1!
1*
1;
1<
b10011 B
1E
b10011 K
1N
b10011 T
1W
b10011 ]
1`
1e
b1 h
1j
1q
#210000000
0!
0*
0<
0E
0N
0W
0`
0q
#215000000
1!
b10 (
1*
b10 1
0;
1<
b10100 B
1E
b10100 K
1N
b10100 T
1W
b10100 ]
1`
b10 d
0e
b10 g
b0 h
0j
1q
#220000000
0!
0*
0<
0E
0N
0W
0`
0q
#225000000
1!
1*
1;
1<
b10101 B
1E
b10101 K
1N
b10101 T
1W
b10101 ]
1`
1e
b1 h
1j
1q
#230000000
0!
0*
0<
0E
0N
0W
0`
0q
#235000000
1!
b11 (
1*
b11 1
0;
1<
b10110 B
1E
b10110 K
1N
b10110 T
1W
b10110 ]
1`
b11 d
0e
b11 g
b0 h
0j
1q
#240000000
0!
0*
0<
0E
0N
0W
0`
0q
#245000000
1!
1*
1;
1<
b10111 B
1E
b10111 K
1N
b10111 T
1W
b10111 ]
1`
1e
b1 h
1j
1q
#250000000
0!
0*
0<
0E
0N
0W
0`
0q
#255000000
1!
b00 (
1*
b00 1
0;
1<
b11000 B
1E
b11000 K
1N
b11000 T
1W
b11000 ]
1`
b00 d
0e
b00 g
b0 h
0j
1q
#260000000
0!
0*
0<
0E
0N
0W
0`
0q
#265000000
1!
1*
1;
1<
b11001 B
1E
b11001 K
1N
b11001 T
1W
b11001 ]
1`
1e
b1 h
1j
1q
#270000000
0!
0*
0<
0E
0N
0W
0`
0q
#275000000
1!
b01 (
1*
b01 1
0;
1<
b11010 B
1E
b11010 K
1N
b11010 T
1W
b11010 ]
1`
b01 d
0e
b01 g
b0 h
0j
1q
#280000000
0!
0*
0<
0E
0N
0W
0`
0q
#285000000
1!
1*
1;
1<
b11011 B
1E
b11011 K
1N
b11011 T
1W
b11011 ]
1`
1e
b1 h
1j
1q
#290000000
0!
0*
0<
0E
0N
0W
0`
0q
#295000000
1!
b10 (
1*
b10 1
0;
1<
b11100 B
1E
b11100 K
1N
b11100 T
1W
b11100 ]
1`
b10 d
0e
b10 g
b0 h
0j
1q
#300000000
0!
0*
0<
0E
0N
0W
0`
0q
#305000000
1!
1*
1;
1<
b11101 B
1E
b11101 K
1N
b11101 T
1W
b11101 ]
1`
1e
b1 h
1j
1q
#310000000
0!
0*
0<
0E
0N
0W
0`
0q
#315000000
1!
b11 (
1*
b11 1
0;
1<
b11110 B
1E
b11110 K
1N
b11110 T
1W
b11110 ]
1`
b11 d
0e
b11 g
b0 h
0j
1q
#320000000
0!
0*
0<
0E
0N
0W
0`
0q
#325000000
1!
1*
1;
1<
b11111 B
1E
b11111 K
1N
b11111 T
1W
b11111 ]
1`
1e
b1 h
1j
1q
#330000000
0!
0*
0<
0E
0N
0W
0`
0q
#335000000
1!
b00 (
1*
b00 1
0;
1<
b100000 B
1E
b100000 K
1N
b100000 T
1W
b100000 ]
1`
b00 d
0e
b00 g
b0 h
0j
1q
#340000000
0!
0*
0<
0E
0N
0W
0`
0q
#345000000
1!
1*
1;
1<
b100001 B
1E
b100001 K
1N
b100001 T
1W
b100001 ]
1`
1e
b1 h
1j
1q
#350000000
0!
0*
0<
0E
0N
0W
0`
0q
#355000000
1!
b01 (
1*
b01 1
0;
1<
b100010 B
1E
b100010 K
1N
b100010 T
1W
b100010 ]
1`
b01 d
0e
b01 g
b0 h
0j
1q
#360000000
0!
0*
0<
0E
0N
0W
0`
0q
#365000000
1!
1*
1;
1<
b100011 B
1E
b100011 K
1N
b100011 T
1W
b100011 ]
1`
1e
b1 h
1j
1q
#370000000
0!
0*
0<
0E
0N
0W
0`
0q
#375000000
1!
b10 (
1*
b10 1
0;
1<
b100100 B
1E
b100100 K
1N
b100100 T
1W
b100100 ]
1`
b10 d
0e
b10 g
b0 h
0j
1q
#380000000
0!
0*
0<
0E
0N
0W
0`
0q
#385000000
1!
1*
1;
1<
b100101 B
1E
b100101 K
1N
b100101 T
1W
b100101 ]
1`
1e
b1 h
1j
1q
#390000000
0!
0*
0<
0E
0N
0W
0`
0q
#395000000
1!
b11 (
1*
b11 1
0;
1<
b100110 B
1E
b100110 K
1N
b100110 T
1W
b100110 ]
1`
b11 d
0e
b11 g
b0 h
0j
1q
