LABS/student_labs_5_8/lab8_cache/src/main_memory_sync.vhd
library ieee;
use ieee.std_logic_1164.all;
use ieee.numeric_std.all;
use work.lab_variant_pkg.all;

entity main_memory_sync is
  port (
    clk_i   : in  std_logic;
    req_i   : in  std_logic;
    we_i    : in  std_logic;
    addr_i  : in  addr_t;
    wdata_i : in  word_t;
    rdata_o : out word_t;
    grant_o : out std_logic
  );
end entity;

architecture rtl of main_memory_sync is
  type mem_t is array (0 to 255) of word_t;

  function init_mem return mem_t is
    variable m : mem_t;
  begin
    for i in 0 to 255 loop
      m(i) := std_logic_vector(to_unsigned(16#1000# + i * 17, DATA_W));
    end loop;
    return m;
  end function;

  signal mem_r   : mem_t := init_mem;
  signal rdata_r : word_t := (others => '0');
  signal grant_r : std_logic := '0';
begin
  process(clk_i)
    variable idx_v : integer range 0 to 255;
  begin
    if rising_edge(clk_i) then
      grant_r <= req_i;
      idx_v := to_integer(unsigned(addr_i(7 downto 0)));
      if req_i = '1' then
        if we_i = '1' then
          mem_r(idx_v) <= wdata_i;
          rdata_r <= wdata_i;
        else
          rdata_r <= mem_r(idx_v);
        end if;
      end if;
    end if;
  end process;

  rdata_o <= rdata_r;
  grant_o <= grant_r;
end architecture;

LABS/student_labs_5_8/lab8_cache/src/cache_direct_mapped.vhd
library ieee;
use ieee.std_logic_1164.all;
use ieee.numeric_std.all;
use work.lab_variant_pkg.all;

entity cache_direct_mapped is
  port (
    clk_i        : in  std_logic;
    rst_i        : in  std_logic;
    cpu_req_i    : in  std_logic;
    cpu_we_i     : in  std_logic;
    cpu_addr_i   : in  addr_t;
    cpu_wdata_i  : in  word_t;
    cpu_rdata_o  : out word_t;
    cpu_ready_o  : out std_logic;
    hit_o        : out std_logic;
    miss_o       : out std_logic;
    ram_req_o    : out std_logic;
    ram_we_o     : out std_logic;
    ram_addr_o   : out addr_t;
    ram_wdata_o  : out word_t;
    ram_rdata_i  : in  word_t;
    ram_grant_i  : in  std_logic
  );
end entity;

architecture rtl of cache_direct_mapped is
  subtype cache_tag_t is std_logic_vector(12 downto 0);
  type cache_state_t is (IDLE, WAIT_READ_GRANT, WAIT_READ_DATA, WAIT_WRITE_GRANT);
  type cache_data_t is array (0 to CACHE_SETS - 1) of word_t;
  type cache_tag_array_t is array (0 to CACHE_SETS - 1) of cache_tag_t;
  type cache_valid_t is array (0 to CACHE_SETS - 1) of std_logic;

  signal state_r      : cache_state_t := IDLE;
  signal data_r       : cache_data_t := (others => (others => '0'));
  signal tag_r        : cache_tag_array_t := (others => (others => '0'));
  signal valid_r      : cache_valid_t := (others => '0');
  signal req_addr_r   : addr_t := (others => '0');
  signal req_wdata_r  : word_t := (others => '0');
  signal index_r      : integer range 0 to CACHE_SETS - 1 := 0;
  signal tag_req_r    : cache_tag_t := (others => '0');
  signal cpu_rdata_r  : word_t := (others => '0');
  signal cpu_ready_r  : std_logic := '0';
  signal hit_r        : std_logic := '0';
  signal miss_r       : std_logic := '0';
  signal ram_req_r    : std_logic := '0';
  signal ram_we_r     : std_logic := '0';
  signal ram_addr_r   : addr_t := (others => '0');
  signal ram_wdata_r  : word_t := (others => '0');

  function cache_index(addr : addr_t) return integer is
  begin
    return to_integer(unsigned(addr(2 downto 0)));
  end function;

  function cache_tag(addr : addr_t) return cache_tag_t is
  begin
    return addr(15 downto 3);
  end function;
begin
  cpu_rdata_o <= cpu_rdata_r;
  cpu_ready_o <= cpu_ready_r;
  hit_o       <= hit_r;
  miss_o      <= miss_r;
  ram_req_o   <= ram_req_r;
  ram_we_o    <= ram_we_r;
  ram_addr_o  <= ram_addr_r;
  ram_wdata_o <= ram_wdata_r;

  process(clk_i)
    variable index_v : integer range 0 to CACHE_SETS - 1;
    variable tag_v   : cache_tag_t;
    variable hit_v   : boolean;
  begin
    if rising_edge(clk_i) then
      if rst_i = '1' then
        state_r     <= IDLE;
        data_r      <= (others => (others => '0'));
        tag_r       <= (others => (others => '0'));
        valid_r     <= (others => '0');
        req_addr_r  <= (others => '0');
        req_wdata_r <= (others => '0');
        index_r     <= 0;
        tag_req_r   <= (others => '0');
        cpu_rdata_r <= (others => '0');
        cpu_ready_r <= '0';
        hit_r       <= '0';
        miss_r      <= '0';
        ram_req_r   <= '0';
        ram_we_r    <= '0';
        ram_addr_r  <= (others => '0');
        ram_wdata_r <= (others => '0');
      else
        cpu_ready_r <= '0';
        hit_r       <= '0';
        miss_r      <= '0';

        case state_r is
          when IDLE =>
            ram_req_r <= '0';
            ram_we_r  <= '0';

            if cpu_req_i = '1' then
              index_v := cache_index(cpu_addr_i);
              tag_v := cache_tag(cpu_addr_i);
              hit_v := valid_r(index_v) = '1' and tag_r(index_v) = tag_v;

              req_addr_r  <= cpu_addr_i;
              req_wdata_r <= cpu_wdata_i;
              index_r     <= index_v;
              tag_req_r   <= tag_v;

              if hit_v and cpu_we_i = '0' then
                cpu_rdata_r <= data_r(index_v);
                cpu_ready_r <= '1';
                hit_r       <= '1';
              elsif cpu_we_i = '1' then
                if hit_v then
                  hit_r <= '1';
                else
                  miss_r <= '1';
                end if;
                data_r(index_v)  <= cpu_wdata_i;
                tag_r(index_v)   <= tag_v;
                valid_r(index_v) <= '1';
                ram_req_r        <= '1';
                ram_we_r         <= '1';
                ram_addr_r       <= cpu_addr_i;
                ram_wdata_r      <= cpu_wdata_i;
                state_r          <= WAIT_WRITE_GRANT;
              else
                ram_req_r   <= '1';
                ram_we_r    <= '0';
                ram_addr_r  <= cpu_addr_i;
                ram_wdata_r <= (others => '0');
                state_r     <= WAIT_READ_GRANT;
                miss_r      <= '1';
              end if;
            end if;

          when WAIT_READ_GRANT =>
            ram_req_r  <= '1';
            ram_we_r   <= '0';
            ram_addr_r <= req_addr_r;
            if ram_grant_i = '1' then
              state_r <= WAIT_READ_DATA;
            end if;

          when WAIT_READ_DATA =>
            ram_req_r <= '0';
            ram_we_r  <= '0';
            data_r(index_r)  <= ram_rdata_i;
            tag_r(index_r)   <= tag_req_r;
            valid_r(index_r) <= '1';
            cpu_rdata_r      <= ram_rdata_i;
            cpu_ready_r      <= '1';
            miss_r           <= '1';
            state_r          <= IDLE;

          when WAIT_WRITE_GRANT =>
            ram_req_r   <= '1';
            ram_we_r    <= '1';
            ram_addr_r  <= req_addr_r;
            ram_wdata_r <= req_wdata_r;
            if ram_grant_i = '1' then
              cpu_ready_r <= '1';
              ram_req_r   <= '0';
              ram_we_r    <= '0';
              state_r     <= IDLE;
            end if;
        end case;
      end if;
    end if;
  end process;
end architecture;

LABS/student_labs_5_8/lab8_cache/src/lab8_cache_top.vhd
library ieee;
use ieee.std_logic_1164.all;
use work.lab_variant_pkg.all;

entity lab8_cache_top is
  port (
    clk_i          : in  std_logic;
    rst_i          : in  std_logic;
    cpu_req_i      : in  std_logic;
    cpu_we_i       : in  std_logic;
    cpu_addr_i     : in  addr_t;
    cpu_wdata_i    : in  word_t;
    cpu_rdata_o    : out word_t;
    cpu_ready_o    : out std_logic;
    hit_o          : out std_logic;
    miss_o         : out std_logic;
    ram_req_dbg_o  : out std_logic;
    ram_we_dbg_o   : out std_logic;
    ram_addr_dbg_o : out addr_t;
    ram_data_dbg_o : out word_t
  );
end entity;

architecture structural of lab8_cache_top is
  signal ram_req_s   : std_logic;
  signal ram_we_s    : std_logic;
  signal ram_addr_s  : addr_t;
  signal ram_wdata_s : word_t;
  signal ram_rdata_s : word_t;
  signal ram_grant_s : std_logic;
begin
  U_CACHE : entity work.cache_direct_mapped
    port map (
      clk_i        => clk_i,
      rst_i        => rst_i,
      cpu_req_i    => cpu_req_i,
      cpu_we_i     => cpu_we_i,
      cpu_addr_i   => cpu_addr_i,
      cpu_wdata_i  => cpu_wdata_i,
      cpu_rdata_o  => cpu_rdata_o,
      cpu_ready_o  => cpu_ready_o,
      hit_o        => hit_o,
      miss_o       => miss_o,
      ram_req_o    => ram_req_s,
      ram_we_o     => ram_we_s,
      ram_addr_o   => ram_addr_s,
      ram_wdata_o  => ram_wdata_s,
      ram_rdata_i  => ram_rdata_s,
      ram_grant_i  => ram_grant_s
    );

  U_RAM : entity work.main_memory_sync
    port map (
      clk_i   => clk_i,
      req_i   => ram_req_s,
      we_i    => ram_we_s,
      addr_i  => ram_addr_s,
      wdata_i => ram_wdata_s,
      rdata_o => ram_rdata_s,
      grant_o => ram_grant_s
    );

  ram_req_dbg_o  <= ram_req_s;
  ram_we_dbg_o   <= ram_we_s;
  ram_addr_dbg_o <= ram_addr_s;
  ram_data_dbg_o <= ram_wdata_s when ram_we_s = '1' else ram_rdata_s;
end architecture;

LABS/student_labs_5_8/lab8_cache/tb/tb_lab8_cache.vhd
library ieee;
use ieee.std_logic_1164.all;
use work.lab_variant_pkg.all;

entity tb_lab8_cache is
end entity;

architecture sim of tb_lab8_cache is
  signal clk          : std_logic := '0';
  signal rst          : std_logic := '1';
  signal cpu_req      : std_logic := '0';
  signal cpu_we       : std_logic := '0';
  signal cpu_addr     : addr_t := (others => '0');
  signal cpu_wdata    : word_t := (others => '0');
  signal cpu_rdata    : word_t;
  signal cpu_ready    : std_logic;
  signal hit          : std_logic;
  signal miss         : std_logic;
  signal ram_req      : std_logic;
  signal ram_we       : std_logic;
  signal ram_addr     : addr_t;
  signal ram_data     : word_t;

  procedure cpu_access(
    signal clk_s       : in std_logic;
    signal req_s       : out std_logic;
    signal we_s        : out std_logic;
    signal addr_s      : out addr_t;
    signal wdata_s     : out word_t;
    signal ready_s     : in std_logic;
    constant is_write  : in boolean;
    constant addr_c    : in addr_t;
    constant wdata_c   : in word_t
  ) is
  begin
    wait until rising_edge(clk_s);
    addr_s  <= addr_c;
    wdata_s <= wdata_c;
    if is_write then
      we_s <= '1';
    else
      we_s <= '0';
    end if;
    req_s <= '1';

    loop
      wait until rising_edge(clk_s);
      wait for 1 ns;
      exit when ready_s = '1';
    end loop;

    req_s <= '0';
    we_s  <= '0';
    wait for 1 ns;
  end procedure;
begin
  clk <= not clk after 5 ns;

  DUT : entity work.lab8_cache_top
    port map (
      clk_i          => clk,
      rst_i          => rst,
      cpu_req_i      => cpu_req,
      cpu_we_i       => cpu_we,
      cpu_addr_i     => cpu_addr,
      cpu_wdata_i    => cpu_wdata,
      cpu_rdata_o    => cpu_rdata,
      cpu_ready_o    => cpu_ready,
      hit_o          => hit,
      miss_o         => miss,
      ram_req_dbg_o  => ram_req,
      ram_we_dbg_o   => ram_we,
      ram_addr_dbg_o => ram_addr,
      ram_data_dbg_o => ram_data
    );

  stimulus : process
  begin
    wait until rising_edge(clk);
    wait until rising_edge(clk);
    rst <= '0';
    wait until rising_edge(clk);
    wait for 1 ns;

    cpu_access(clk, cpu_req, cpu_we, cpu_addr, cpu_wdata, cpu_ready, false, x"0010", x"0000");
    assert cpu_rdata = x"1110"
      report "First read from 0010h must be filled from main memory" severity failure;
    assert miss = '1'
      report "First read from 0010h must be a miss" severity failure;

    cpu_access(clk, cpu_req, cpu_we, cpu_addr, cpu_wdata, cpu_ready, false, x"0010", x"0000");
    assert cpu_rdata = x"1110" and hit = '1'
      report "Second read from 0010h must be a hit" severity failure;

    cpu_access(clk, cpu_req, cpu_we, cpu_addr, cpu_wdata, cpu_ready, true, x"0010", x"ABCD");
    cpu_access(clk, cpu_req, cpu_we, cpu_addr, cpu_wdata, cpu_ready, false, x"0010", x"0000");
    assert cpu_rdata = x"ABCD"
      report "Write-through hit must update the cached word" severity failure;

    cpu_access(clk, cpu_req, cpu_we, cpu_addr, cpu_wdata, cpu_ready, false, x"0018", x"0000");
    assert cpu_rdata = x"1198" and miss = '1'
      report "Direct mapped cache must replace the line with the same index" severity failure;

    cpu_access(clk, cpu_req, cpu_we, cpu_addr, cpu_wdata, cpu_ready, false, x"0010", x"0000");
    assert cpu_rdata = x"ABCD" and miss = '1'
      report "Reading the replaced direct-mapped line must fetch it again from RAM" severity failure;

    assert false report "tb_lab8_cache: TEST PASSED" severity note;
    wait;
  end process;
end architecture;

LABS/student_labs_5_8/sim/vcd/lab8_cache.vcd
$date
  Sun May 17 14:14:04 2026
$end
$version
  GHDL v0
$end
$timescale
  1 fs
$end
$scope module standard $end
$upscope $end
$scope module textio $end
$upscope $end
$scope module std_logic_1164 $end
$upscope $end
$scope module numeric_std $end
$upscope $end
$scope module lab_variant_pkg $end
$upscope $end
$scope module tb_lab8_cache $end
$var reg 1 ! clk $end
$var reg 1 " rst $end
$var reg 1 # cpu_req $end
$var reg 1 $ cpu_we $end
$var reg 16 % cpu_addr[15:0] $end
$var reg 16 & cpu_wdata[15:0] $end
$var reg 16 ' cpu_rdata[15:0] $end
$var reg 1 ( cpu_ready $end
$var reg 1 ) hit $end
$var reg 1 * miss $end
$var reg 1 + ram_req $end
$var reg 1 , ram_we $end
$var reg 16 - ram_addr[15:0] $end
$var reg 16 . ram_data[15:0] $end
$scope module dut $end
$var reg 1 / clk_i $end
$var reg 1 0 rst_i $end
$var reg 1 1 cpu_req_i $end
$var reg 1 2 cpu_we_i $end
$var reg 16 3 cpu_addr_i[15:0] $end
$var reg 16 4 cpu_wdata_i[15:0] $end
$var reg 16 5 cpu_rdata_o[15:0] $end
$var reg 1 6 cpu_ready_o $end
$var reg 1 7 hit_o $end
$var reg 1 8 miss_o $end
$var reg 1 9 ram_req_dbg_o $end
$var reg 1 : ram_we_dbg_o $end
$var reg 16 ; ram_addr_dbg_o[15:0] $end
$var reg 16 < ram_data_dbg_o[15:0] $end
$var reg 1 = ram_req_s $end
$var reg 1 > ram_we_s $end
$var reg 16 ? ram_addr_s[15:0] $end
$var reg 16 @ ram_wdata_s[15:0] $end
$var reg 16 A ram_rdata_s[15:0] $end
$var reg 1 B ram_grant_s $end
$scope module u_cache $end
$var reg 1 C clk_i $end
$var reg 1 D rst_i $end
$var reg 1 E cpu_req_i $end
$var reg 1 F cpu_we_i $end
$var reg 16 G cpu_addr_i[15:0] $end
$var reg 16 H cpu_wdata_i[15:0] $end
$var reg 16 I cpu_rdata_o[15:0] $end
$var reg 1 J cpu_ready_o $end
$var reg 1 K hit_o $end
$var reg 1 L miss_o $end
$var reg 1 M ram_req_o $end
$var reg 1 N ram_we_o $end
$var reg 16 O ram_addr_o[15:0] $end
$var reg 16 P ram_wdata_o[15:0] $end
$var reg 16 Q ram_rdata_i[15:0] $end
$var reg 1 R ram_grant_i $end
$comment state_r is not handled $end
$comment data_r is not handled $end
$comment tag_r is not handled $end
$var reg 8 S valid_r[0:7] $end
$var reg 16 T req_addr_r[15:0] $end
$var reg 16 U req_wdata_r[15:0] $end
$var integer 32 V index_r $end
$var reg 13 W tag_req_r[12:0] $end
$var reg 16 X cpu_rdata_r[15:0] $end
$var reg 1 Y cpu_ready_r $end
$var reg 1 Z hit_r $end
$var reg 1 [ miss_r $end
$var reg 1 \ ram_req_r $end
$var reg 1 ] ram_we_r $end
$var reg 16 ^ ram_addr_r[15:0] $end
$var reg 16 _ ram_wdata_r[15:0] $end
$upscope $end
$scope module u_ram $end
$var reg 1 ` clk_i $end
$var reg 1 a req_i $end
$var reg 1 b we_i $end
$var reg 16 c addr_i[15:0] $end
$var reg 16 d wdata_i[15:0] $end
$var reg 16 e rdata_o[15:0] $end
$var reg 1 f grant_o $end
$comment mem_r is not handled $end
$var reg 16 g rdata_r[15:0] $end
$var reg 1 h grant_r $end
$upscope $end
$upscope $end
$upscope $end
$enddefinitions $end
#0
0!
1"
0#
0$
b0000000000000000 %
b0000000000000000 &
b0000000000000000 '
0(
0)
0*
0+
0,
b0000000000000000 -
b0000000000000000 .
0/
10
01
02
b0000000000000000 3
b0000000000000000 4
b0000000000000000 5
06
07
08
09
0:
b0000000000000000 ;
b0000000000000000 <
0=
0>
b0000000000000000 ?
b0000000000000000 @
b0000000000000000 A
0B
0C
1D
0E
0F
b0000000000000000 G
b0000000000000000 H
b0000000000000000 I
0J
0K
0L
0M
0N
b0000000000000000 O
b0000000000000000 P
b0000000000000000 Q
0R
b00000000 S
b0000000000000000 T
b0000000000000000 U
b0 V
b0000000000000 W
b0000000000000000 X
0Y
0Z
0[
0\
0]
b0000000000000000 ^
b0000000000000000 _
0`
0a
0b
b0000000000000000 c
b0000000000000000 d
b0000000000000000 e
0f
b0000000000000000 g
0h
#5000000
1!
1/
1C
1`
#10000000
0!
0/
0C
0`
#15000000
1!
0"
1/
00
1C
0D
1`
#20000000
0!
0/
0C
0`
#25000000
1!
1/
1C
1`
#30000000
0!
0/
0C
0`
#35000000
1!
1#
b0000000000010000 %
1/
11
b0000000000010000 3
1C
1E
b0000000000010000 G
1`
#40000000
0!
0/
0C
0`
#45000000
1!
1*
1+
b0000000000010000 -
1/
18
19
b0000000000010000 ;
1=
b0000000000010000 ?
1C
1L
1M
b0000000000010000 O
b0000000000010000 T
b0000000000010 W
1[
1\
b0000000000010000 ^
1`
1a
b0000000000010000 c
#50000000
0!
0/
0C
0`
#55000000
1!
0*
b0001000100010000 .
1/
08
b0001000100010000 <
b0001000100010000 A
1B
1C
0L
b0001000100010000 Q
1R
0[
1`
b0001000100010000 e
1f
b0001000100010000 g
1h
#60000000
0!
0/
0C
0`
#65000000
1!
1/
1C
1`
#70000000
0!
0/
0C
0`
#75000000
1!
b0001000100010000 '
1(
1*
0+
1/
b0001000100010000 5
16
18
09
0=
1C
b0001000100010000 I
1J
1L
0M
b10000000 S
b0001000100010000 X
1Y
1[
0\
1`
0a
#76000000
0#
01
0E
#80000000
0!
0/
0C
0`
#85000000
1!
1#
0(
0*
1/
11
06
08
0B
1C
1E
0J
0L
0R
0Y
0[
1`
0f
0h
#90000000
0!
0/
0C
0`
#95000000
1!
1(
1)
1/
16
17
1C
1J
1K
1Y
1Z
1`
#96000000
0#
01
0E
#100000000
0!
0/
0C
0`
#105000000
1!
1#
1$
b1010101111001101 &
0(
0)
1/
11
12
b1010101111001101 4
06
07
1C
1E
1F
b1010101111001101 H
0J
0K
0Y
0Z
1`
#110000000
0!
0/
0C
0`
#115000000
1!
1)
1+
1,
b1010101111001101 .
1/
17
19
1:
b1010101111001101 <
1=
1>
b1010101111001101 @
1C
1K
1M
1N
b1010101111001101 P
b1010101111001101 U
1Z
1\
1]
b1010101111001101 _
1`
1a
1b
b1010101111001101 d
#120000000
0!
0/
0C
0`
#125000000
1!
0)
1/
07
b1010101111001101 A
1B
1C
0K
b1010101111001101 Q
1R
0Z
1`
b1010101111001101 e
1f
b1010101111001101 g
1h
#130000000
0!
0/
0C
0`
#135000000
1!
1(
0+
0,
1/
16
09
0:
0=
0>
1C
1J
0M
0N
1Y
0\
0]
1`
0a
0b
#136000000
0#
0$
01
02
0E
0F
#140000000
0!
0/
0C
0`
#145000000
1!
1#
b0000000000000000 &
0(
1/
11
b0000000000000000 4
06
0B
1C
1E
b0000000000000000 H
0J
0R
0Y
1`
0f
0h
#150000000
0!
0/
0C
0`
#155000000
1!
b1010101111001101 '
1(
1)
1/
b1010101111001101 5
16
17
1C
b1010101111001101 I
1J
1K
b0000000000000000 U
b1010101111001101 X
1Y
1Z
1`
#156000000
0#
01
0E
#160000000
0!
0/
0C
0`
#165000000
1!
1#
b0000000000011000 %
0(
0)
1/
11
b0000000000011000 3
06
07
1C
1E
b0000000000011000 G
0J
0K
0Y
0Z
1`
#170000000
0!
0/
0C
0`
#175000000
1!
1*
1+
b0000000000011000 -
1/
18
19
b0000000000011000 ;
1=
b0000000000011000 ?
b0000000000000000 @
1C
1L
1M
b0000000000011000 O
b0000000000000000 P
b0000000000011000 T
b0000000000011 W
1[
1\
b0000000000011000 ^
b0000000000000000 _
1`
1a
b0000000000011000 c
b0000000000000000 d
#180000000
0!
0/
0C
0`
#185000000
1!
0*
b0001000110011000 .
1/
08
b0001000110011000 <
b0001000110011000 A
1B
1C
0L
b0001000110011000 Q
1R
0[
1`
b0001000110011000 e
1f
b0001000110011000 g
1h
#190000000
0!
0/
0C
0`
#195000000
1!
1/
1C
1`
#200000000
0!
0/
0C
0`
#205000000
1!
b0001000110011000 '
1(
1*
0+
1/
b0001000110011000 5
16
18
09
0=
1C
b0001000110011000 I
1J
1L
0M
b0001000110011000 X
1Y
1[
0\
1`
0a
#206000000
0#
01
0E
#210000000
0!
0/
0C
0`
#215000000
1!
1#
b0000000000010000 %
0(
0*
1/
11
b0000000000010000 3
06
08
0B
1C
1E
b0000000000010000 G
0J
0L
0R
0Y
0[
1`
0f
0h
#220000000
0!
0/
0C
0`
#225000000
1!
1*
1+
b0000000000010000 -
1/
18
19
b0000000000010000 ;
1=
b0000000000010000 ?
1C
1L
1M
b0000000000010000 O
b0000000000010000 T
b0000000000010 W
1[
1\
b0000000000010000 ^
1`
1a
b0000000000010000 c
#230000000
0!
0/
0C
0`
#235000000
1!
0*
b1010101111001101 .
1/
08
b1010101111001101 <
b1010101111001101 A
1B
1C
0L
b1010101111001101 Q
1R
0[
1`
b1010101111001101 e
1f
b1010101111001101 g
1h
#240000000
0!
0/
0C
0`
#245000000
1!
1/
1C
1`
#250000000
0!
0/
0C
0`
#255000000
1!
b1010101111001101 '
1(
1*
0+
1/
b1010101111001101 5
16
18
09
0=
1C
b1010101111001101 I
1J
1L
0M
b1010101111001101 X
1Y
1[
0\
1`
0a
#256000000
0#
01
0E
#260000000
0!
0/
0C
0`
#265000000
1!
0(
0*
1/
06
08
0B
1C
0J
0L
0R
0Y
0[
1`
0f
0h
