LABS/student_labs_5_8/lab8_cache/src/main_memory_sync.vhd
library ieee;
use ieee.std_logic_1164.all;
use ieee.numeric_std.all;
use work.lab_variant_pkg.all;

entity main_memory_sync is
  port (
    clk_i   : in  std_logic;
    req_i   : in  std_logic;
    we_i    : in  std_logic;
    addr_i  : in  addr_t;
    wdata_i : in  word_t;
    rdata_o : out word_t;
    grant_o : out std_logic
  );
end entity;

architecture rtl of main_memory_sync is
  type mem_t is array (0 to 255) of word_t;

  function init_mem return mem_t is
    variable m : mem_t;
  begin
    for i in 0 to 255 loop
      m(i) := std_logic_vector(to_unsigned(16#1000# + i * 17, DATA_W));
    end loop;
    return m;
  end function;

  signal mem_r   : mem_t := init_mem;
  signal rdata_r : word_t := (others => '0');
  signal grant_r : std_logic := '0';
begin
  process(clk_i)
    variable idx_v : integer range 0 to 255;
  begin
    if rising_edge(clk_i) then
      grant_r <= req_i;
      idx_v := to_integer(unsigned(addr_i(7 downto 0)));
      if req_i = '1' then
        if we_i = '1' then
          mem_r(idx_v) <= wdata_i;
          rdata_r <= wdata_i;
        else
          rdata_r <= mem_r(idx_v);
        end if;
      end if;
    end if;
  end process;

  rdata_o <= rdata_r;
  grant_o <= grant_r;
end architecture;

LABS/student_labs_5_8/lab8_cache/src/cache4way_age.vhd
library ieee;
use ieee.std_logic_1164.all;
use ieee.numeric_std.all;
use work.lab_variant_pkg.all;

entity cache4way_age is
  port (
    clk_i        : in  std_logic;
    rst_i        : in  std_logic;
    cpu_req_i    : in  std_logic;
    cpu_we_i     : in  std_logic;
    cpu_addr_i   : in  addr_t;
    cpu_wdata_i  : in  word_t;
    cpu_rdata_o  : out word_t;
    cpu_ready_o  : out std_logic;
    hit_o        : out std_logic;
    miss_o       : out std_logic;
    ram_req_o    : out std_logic;
    ram_we_o     : out std_logic;
    ram_addr_o   : out addr_t;
    ram_wdata_o  : out word_t;
    ram_rdata_i  : in  word_t;
    ram_grant_i  : in  std_logic
  );
end entity;

architecture rtl of cache4way_age is
  subtype cache_tag_t is std_logic_vector(11 downto 0);
  type cache_state_t is (IDLE, WAIT_READ_GRANT, WAIT_READ_DATA, WAIT_WRITE_GRANT);
  type set_way_word_t is array (0 to CACHE_SETS - 1, 0 to CACHE_WAYS - 1) of word_t;
  type set_way_tag_t is array (0 to CACHE_SETS - 1, 0 to CACHE_WAYS - 1) of cache_tag_t;
  type set_way_age_t is array (0 to CACHE_SETS - 1, 0 to CACHE_WAYS - 1) of unsigned(1 downto 0);
  type set_way_valid_t is array (0 to CACHE_SETS - 1, 0 to CACHE_WAYS - 1) of std_logic;

  signal state_r      : cache_state_t := IDLE;
  signal data_r       : set_way_word_t := (others => (others => (others => '0')));
  signal tag_r        : set_way_tag_t := (others => (others => (others => '0')));
  signal age_r        : set_way_age_t := (others => (others => (others => '0')));
  signal valid_r      : set_way_valid_t := (others => (others => '0'));

  signal req_addr_r   : addr_t := (others => '0');
  signal req_wdata_r  : word_t := (others => '0');
  signal write_hit_r  : std_logic := '0';
  signal victim_r     : integer range 0 to CACHE_WAYS - 1 := 0;
  signal set_r        : integer range 0 to CACHE_SETS - 1 := 0;
  signal tag_req_r    : cache_tag_t := (others => '0');

  signal cpu_rdata_r  : word_t := (others => '0');
  signal cpu_ready_r  : std_logic := '0';
  signal hit_r        : std_logic := '0';
  signal miss_r       : std_logic := '0';
  signal ram_req_r    : std_logic := '0';
  signal ram_we_r     : std_logic := '0';
  signal ram_addr_r   : addr_t := (others => '0');
  signal ram_wdata_r  : word_t := (others => '0');

  function cache_set(addr : addr_t) return integer is
  begin
    return to_integer(unsigned(addr(3 downto 0)));
  end function;

  function cache_tag(addr : addr_t) return cache_tag_t is
  begin
    return addr(15 downto 4);
  end function;

  function inc_age(v : unsigned(1 downto 0)) return unsigned is
  begin
    if v = "11" then
      return v;
    end if;
    return v + 1;
  end function;
begin
  cpu_rdata_o <= cpu_rdata_r;
  cpu_ready_o <= cpu_ready_r;
  hit_o       <= hit_r;
  miss_o      <= miss_r;
  ram_req_o   <= ram_req_r;
  ram_we_o    <= ram_we_r;
  ram_addr_o  <= ram_addr_r;
  ram_wdata_o <= ram_wdata_r;

  process(clk_i)
    variable set_v    : integer range 0 to CACHE_SETS - 1;
    variable hit_v    : boolean;
    variable hit_way  : integer range 0 to CACHE_WAYS - 1;
    variable victim_v : integer range 0 to CACHE_WAYS - 1;
    variable tag_v    : cache_tag_t;
  begin
    if rising_edge(clk_i) then
      if rst_i = '1' then
        state_r     <= IDLE;
        data_r      <= (others => (others => (others => '0')));
        tag_r       <= (others => (others => (others => '0')));
        age_r       <= (others => (others => (others => '0')));
        valid_r     <= (others => (others => '0'));
        req_addr_r  <= (others => '0');
        req_wdata_r <= (others => '0');
        write_hit_r <= '0';
        victim_r    <= 0;
        set_r       <= 0;
        tag_req_r   <= (others => '0');
        cpu_rdata_r <= (others => '0');
        cpu_ready_r <= '0';
        hit_r       <= '0';
        miss_r      <= '0';
        ram_req_r   <= '0';
        ram_we_r    <= '0';
        ram_addr_r  <= (others => '0');
        ram_wdata_r <= (others => '0');
      else
        cpu_ready_r <= '0';
        hit_r       <= '0';
        miss_r      <= '0';

        case state_r is
          when IDLE =>
            ram_req_r <= '0';
            ram_we_r  <= '0';

            if cpu_req_i = '1' and cpu_ready_r = '0' then
              set_v := cache_set(cpu_addr_i);
              tag_v := cache_tag(cpu_addr_i);
              hit_v := false;
              hit_way := 0;
              victim_v := 0;

              for way in 0 to CACHE_WAYS - 1 loop
                if valid_r(set_v, way) = '1' and tag_r(set_v, way) = tag_v then
                  hit_v := true;
                  hit_way := way;
                end if;
              end loop;

              for way in 0 to CACHE_WAYS - 1 loop
                if valid_r(set_v, way) = '0' then
                  victim_v := way;
                elsif valid_r(set_v, victim_v) = '1' and age_r(set_v, way) > age_r(set_v, victim_v) then
                  victim_v := way;
                end if;
              end loop;

              req_addr_r  <= cpu_addr_i;
              req_wdata_r <= cpu_wdata_i;
              write_hit_r <= '0';
              victim_r    <= victim_v;
              set_r       <= set_v;
              tag_req_r   <= tag_v;

              if hit_v and cpu_we_i = '0' then
                cpu_rdata_r <= data_r(set_v, hit_way);
                cpu_ready_r <= '1';
                hit_r       <= '1';
              elsif cpu_we_i = '1' then
                if hit_v then
                  data_r(set_v, hit_way) <= cpu_wdata_i;
                  victim_v := hit_way;
                  write_hit_r <= '1';
                  hit_r <= '1';
                else
                  miss_r <= '1';
                end if;
                ram_req_r   <= '1';
                ram_we_r    <= '1';
                ram_addr_r  <= cpu_addr_i;
                ram_wdata_r <= cpu_wdata_i;
                victim_r    <= victim_v;
                state_r     <= WAIT_WRITE_GRANT;
              else
                ram_req_r   <= '1';
                ram_we_r    <= '0';
                ram_addr_r  <= cpu_addr_i;
                ram_wdata_r <= (others => '0');
                state_r     <= WAIT_READ_GRANT;
                miss_r      <= '1';
              end if;
            end if;

          when WAIT_READ_GRANT =>
            ram_req_r  <= '1';
            ram_we_r   <= '0';
            ram_addr_r <= req_addr_r;
            if ram_grant_i = '1' then
              state_r <= WAIT_READ_DATA;
            end if;

          when WAIT_READ_DATA =>
            ram_req_r <= '0';
            ram_we_r  <= '0';
            data_r(set_r, victim_r)  <= ram_rdata_i;
            tag_r(set_r, victim_r)   <= tag_req_r;
            valid_r(set_r, victim_r) <= '1';
            age_r(set_r, victim_r)   <= (others => '0');
            for way in 0 to CACHE_WAYS - 1 loop
              if way /= victim_r and valid_r(set_r, way) = '1' then
                age_r(set_r, way) <= inc_age(age_r(set_r, way));
              end if;
            end loop;
            cpu_rdata_r <= ram_rdata_i;
            cpu_ready_r <= '1';
            miss_r      <= '1';
            state_r     <= IDLE;

          when WAIT_WRITE_GRANT =>
            ram_req_r   <= '1';
            ram_we_r    <= '1';
            ram_addr_r  <= req_addr_r;
            ram_wdata_r <= req_wdata_r;
            if ram_grant_i = '1' then
              if write_hit_r = '0' then
                data_r(set_r, victim_r)  <= req_wdata_r;
                tag_r(set_r, victim_r)   <= tag_req_r;
                valid_r(set_r, victim_r) <= '1';
                age_r(set_r, victim_r)   <= (others => '0');
                for way in 0 to CACHE_WAYS - 1 loop
                  if way /= victim_r and valid_r(set_r, way) = '1' then
                    age_r(set_r, way) <= inc_age(age_r(set_r, way));
                  end if;
                end loop;
              end if;
              cpu_ready_r <= '1';
              state_r     <= IDLE;
              ram_req_r   <= '0';
              ram_we_r    <= '0';
            end if;
        end case;
      end if;
    end if;
  end process;
end architecture;

LABS/student_labs_5_8/lab8_cache/src/lab8_cache_top.vhd
library ieee;
use ieee.std_logic_1164.all;
use work.lab_variant_pkg.all;

entity lab8_cache_top is
  port (
    clk_i          : in  std_logic;
    rst_i          : in  std_logic;
    cpu_req_i      : in  std_logic;
    cpu_we_i       : in  std_logic;
    cpu_addr_i     : in  addr_t;
    cpu_wdata_i    : in  word_t;
    cpu_rdata_o    : out word_t;
    cpu_ready_o    : out std_logic;
    hit_o          : out std_logic;
    miss_o         : out std_logic;
    ram_req_dbg_o  : out std_logic;
    ram_we_dbg_o   : out std_logic;
    ram_addr_dbg_o : out addr_t;
    ram_data_dbg_o : out word_t
  );
end entity;

architecture structural of lab8_cache_top is
  signal ram_req_s   : std_logic;
  signal ram_we_s    : std_logic;
  signal ram_addr_s  : addr_t;
  signal ram_wdata_s : word_t;
  signal ram_rdata_s : word_t;
  signal ram_grant_s : std_logic;
begin
  U_CACHE : entity work.cache4way_age
    port map (
      clk_i        => clk_i,
      rst_i        => rst_i,
      cpu_req_i    => cpu_req_i,
      cpu_we_i     => cpu_we_i,
      cpu_addr_i   => cpu_addr_i,
      cpu_wdata_i  => cpu_wdata_i,
      cpu_rdata_o  => cpu_rdata_o,
      cpu_ready_o  => cpu_ready_o,
      hit_o        => hit_o,
      miss_o       => miss_o,
      ram_req_o    => ram_req_s,
      ram_we_o     => ram_we_s,
      ram_addr_o   => ram_addr_s,
      ram_wdata_o  => ram_wdata_s,
      ram_rdata_i  => ram_rdata_s,
      ram_grant_i  => ram_grant_s
    );

  U_RAM : entity work.main_memory_sync
    port map (
      clk_i   => clk_i,
      req_i   => ram_req_s,
      we_i    => ram_we_s,
      addr_i  => ram_addr_s,
      wdata_i => ram_wdata_s,
      rdata_o => ram_rdata_s,
      grant_o => ram_grant_s
    );

  ram_req_dbg_o  <= ram_req_s;
  ram_we_dbg_o   <= ram_we_s;
  ram_addr_dbg_o <= ram_addr_s;
  ram_data_dbg_o <= ram_wdata_s when ram_we_s = '1' else ram_rdata_s;
end architecture;

LABS/student_labs_5_8/lab8_cache/tb/tb_lab8_cache.vhd
library ieee;
use ieee.std_logic_1164.all;
use work.lab_variant_pkg.all;

entity tb_lab8_cache is
end entity;

architecture sim of tb_lab8_cache is
  signal clk          : std_logic := '0';
  signal rst          : std_logic := '1';
  signal cpu_req      : std_logic := '0';
  signal cpu_we       : std_logic := '0';
  signal cpu_addr     : addr_t := (others => '0');
  signal cpu_wdata    : word_t := (others => '0');
  signal cpu_rdata    : word_t;
  signal cpu_ready    : std_logic;
  signal hit          : std_logic;
  signal miss         : std_logic;
  signal ram_req      : std_logic;
  signal ram_we       : std_logic;
  signal ram_addr     : addr_t;
  signal ram_data     : word_t;

  procedure cpu_access(
    signal clk_s       : in std_logic;
    signal req_s       : out std_logic;
    signal we_s        : out std_logic;
    signal addr_s      : out addr_t;
    signal wdata_s     : out word_t;
    signal ready_s     : in std_logic;
    constant is_write  : in boolean;
    constant addr_c    : in addr_t;
    constant wdata_c   : in word_t
  ) is
  begin
    wait until rising_edge(clk_s);
    addr_s  <= addr_c;
    wdata_s <= wdata_c;
    if is_write then
      we_s <= '1';
    else
      we_s <= '0';
    end if;
    req_s <= '1';

    loop
      wait until rising_edge(clk_s);
      wait for 1 ns;
      exit when ready_s = '1';
    end loop;

    req_s <= '0';
    we_s  <= '0';
    wait for 1 ns;
  end procedure;
begin
  clk <= not clk after 5 ns;

  DUT : entity work.lab8_cache_top
    port map (
      clk_i          => clk,
      rst_i          => rst,
      cpu_req_i      => cpu_req,
      cpu_we_i       => cpu_we,
      cpu_addr_i     => cpu_addr,
      cpu_wdata_i    => cpu_wdata,
      cpu_rdata_o    => cpu_rdata,
      cpu_ready_o    => cpu_ready,
      hit_o          => hit,
      miss_o         => miss,
      ram_req_dbg_o  => ram_req,
      ram_we_dbg_o   => ram_we,
      ram_addr_dbg_o => ram_addr,
      ram_data_dbg_o => ram_data
    );

  stimulus : process
  begin
    wait until rising_edge(clk);
    wait until rising_edge(clk);
    rst <= '0';
    wait until rising_edge(clk);
    wait for 1 ns;

    cpu_access(clk, cpu_req, cpu_we, cpu_addr, cpu_wdata, cpu_ready, false, x"0010", x"0000");
    assert cpu_rdata = x"1110"
      report "First read from 0010h must be filled from main memory" severity failure;
    assert miss = '1'
      report "First read from 0010h must be a miss" severity failure;

    cpu_access(clk, cpu_req, cpu_we, cpu_addr, cpu_wdata, cpu_ready, false, x"0010", x"0000");
    assert cpu_rdata = x"1110" and hit = '1'
      report "Second read from 0010h must be a hit" severity failure;

    cpu_access(clk, cpu_req, cpu_we, cpu_addr, cpu_wdata, cpu_ready, true, x"0010", x"ABCD");
    cpu_access(clk, cpu_req, cpu_we, cpu_addr, cpu_wdata, cpu_ready, false, x"0010", x"0000");
    assert cpu_rdata = x"ABCD"
      report "Write-through hit must update the cached word" severity failure;

    cpu_access(clk, cpu_req, cpu_we, cpu_addr, cpu_wdata, cpu_ready, false, x"0020", x"0000");
    cpu_access(clk, cpu_req, cpu_we, cpu_addr, cpu_wdata, cpu_ready, false, x"0030", x"0000");
    cpu_access(clk, cpu_req, cpu_we, cpu_addr, cpu_wdata, cpu_ready, false, x"0040", x"0000");
    cpu_access(clk, cpu_req, cpu_we, cpu_addr, cpu_wdata, cpu_ready, false, x"0050", x"0000");

    cpu_access(clk, cpu_req, cpu_we, cpu_addr, cpu_wdata, cpu_ready, false, x"0010", x"0000");
    assert cpu_rdata = x"ABCD" and miss = '1'
      report "Oldest stored line must be replaced, so 0010h is fetched again from RAM" severity failure;

    assert false report "tb_lab8_cache: TEST PASSED" severity note;
    wait;
  end process;
end architecture;

LABS/student_labs_5_8/sim/vcd/lab8_cache.vcd
$date
  Thu May 14 23:23:56 2026
$end
$version
  GHDL v0
$end
$timescale
  1 fs
$end
$scope module standard $end
$upscope $end
$scope module textio $end
$upscope $end
$scope module std_logic_1164 $end
$upscope $end
$scope module numeric_std $end
$upscope $end
$scope module lab_variant_pkg $end
$upscope $end
$scope module tb_lab8_cache $end
$var reg 1 ! clk $end
$var reg 1 " rst $end
$var reg 1 # cpu_req $end
$var reg 1 $ cpu_we $end
$var reg 16 % cpu_addr[15:0] $end
$var reg 16 & cpu_wdata[15:0] $end
$var reg 16 ' cpu_rdata[15:0] $end
$var reg 1 ( cpu_ready $end
$var reg 1 ) hit $end
$var reg 1 * miss $end
$var reg 1 + ram_req $end
$var reg 1 , ram_we $end
$var reg 16 - ram_addr[15:0] $end
$var reg 16 . ram_data[15:0] $end
$scope module dut $end
$var reg 1 / clk_i $end
$var reg 1 0 rst_i $end
$var reg 1 1 cpu_req_i $end
$var reg 1 2 cpu_we_i $end
$var reg 16 3 cpu_addr_i[15:0] $end
$var reg 16 4 cpu_wdata_i[15:0] $end
$var reg 16 5 cpu_rdata_o[15:0] $end
$var reg 1 6 cpu_ready_o $end
$var reg 1 7 hit_o $end
$var reg 1 8 miss_o $end
$var reg 1 9 ram_req_dbg_o $end
$var reg 1 : ram_we_dbg_o $end
$var reg 16 ; ram_addr_dbg_o[15:0] $end
$var reg 16 < ram_data_dbg_o[15:0] $end
$var reg 1 = ram_req_s $end
$var reg 1 > ram_we_s $end
$var reg 16 ? ram_addr_s[15:0] $end
$var reg 16 @ ram_wdata_s[15:0] $end
$var reg 16 A ram_rdata_s[15:0] $end
$var reg 1 B ram_grant_s $end
$scope module u_cache $end
$var reg 1 C clk_i $end
$var reg 1 D rst_i $end
$var reg 1 E cpu_req_i $end
$var reg 1 F cpu_we_i $end
$var reg 16 G cpu_addr_i[15:0] $end
$var reg 16 H cpu_wdata_i[15:0] $end
$var reg 16 I cpu_rdata_o[15:0] $end
$var reg 1 J cpu_ready_o $end
$var reg 1 K hit_o $end
$var reg 1 L miss_o $end
$var reg 1 M ram_req_o $end
$var reg 1 N ram_we_o $end
$var reg 16 O ram_addr_o[15:0] $end
$var reg 16 P ram_wdata_o[15:0] $end
$var reg 16 Q ram_rdata_i[15:0] $end
$var reg 1 R ram_grant_i $end
$comment state_r is not handled $end
$comment data_r is not handled $end
$comment tag_r is not handled $end
$comment age_r is not handled $end
$comment valid_r is not handled $end
$var reg 16 S req_addr_r[15:0] $end
$var reg 16 T req_wdata_r[15:0] $end
$var reg 1 U write_hit_r $end
$var integer 32 V victim_r $end
$var integer 32 W set_r $end
$var reg 12 X tag_req_r[11:0] $end
$var reg 16 Y cpu_rdata_r[15:0] $end
$var reg 1 Z cpu_ready_r $end
$var reg 1 [ hit_r $end
$var reg 1 \ miss_r $end
$var reg 1 ] ram_req_r $end
$var reg 1 ^ ram_we_r $end
$var reg 16 _ ram_addr_r[15:0] $end
$var reg 16 ` ram_wdata_r[15:0] $end
$upscope $end
$scope module u_ram $end
$var reg 1 a clk_i $end
$var reg 1 b req_i $end
$var reg 1 c we_i $end
$var reg 16 d addr_i[15:0] $end
$var reg 16 e wdata_i[15:0] $end
$var reg 16 f rdata_o[15:0] $end
$var reg 1 g grant_o $end
$comment mem_r is not handled $end
$var reg 16 h rdata_r[15:0] $end
$var reg 1 i grant_r $end
$upscope $end
$upscope $end
$upscope $end
$enddefinitions $end
#0
0!
1"
0#
0$
b0000000000000000 %
b0000000000000000 &
b0000000000000000 '
0(
0)
0*
0+
0,
b0000000000000000 -
b0000000000000000 .
0/
10
01
02
b0000000000000000 3
b0000000000000000 4
b0000000000000000 5
06
07
08
09
0:
b0000000000000000 ;
b0000000000000000 <
0=
0>
b0000000000000000 ?
b0000000000000000 @
b0000000000000000 A
0B
0C
1D
0E
0F
b0000000000000000 G
b0000000000000000 H
b0000000000000000 I
0J
0K
0L
0M
0N
b0000000000000000 O
b0000000000000000 P
b0000000000000000 Q
0R
b0000000000000000 S
b0000000000000000 T
0U
b0 V
b0 W
b000000000000 X
b0000000000000000 Y
0Z
0[
0\
0]
0^
b0000000000000000 _
b0000000000000000 `
0a
0b
0c
b0000000000000000 d
b0000000000000000 e
b0000000000000000 f
0g
b0000000000000000 h
0i
#5000000
1!
1/
1C
1a
#10000000
0!
0/
0C
0a
#15000000
1!
0"
1/
00
1C
0D
1a
#20000000
0!
0/
0C
0a
#25000000
1!
1/
1C
1a
#30000000
0!
0/
0C
0a
#35000000
1!
1#
b0000000000010000 %
1/
11
b0000000000010000 3
1C
1E
b0000000000010000 G
1a
#40000000
0!
0/
0C
0a
#45000000
1!
1*
1+
b0000000000010000 -
1/
18
19
b0000000000010000 ;
1=
b0000000000010000 ?
1C
1L
1M
b0000000000010000 O
b0000000000010000 S
b11 V
b000000000001 X
1\
1]
b0000000000010000 _
1a
1b
b0000000000010000 d
#50000000
0!
0/
0C
0a
#55000000
1!
0*
b0001000100010000 .
1/
08
b0001000100010000 <
b0001000100010000 A
1B
1C
0L
b0001000100010000 Q
1R
0\
1a
b0001000100010000 f
1g
b0001000100010000 h
1i
#60000000
0!
0/
0C
0a
#65000000
1!
1/
1C
1a
#70000000
0!
0/
0C
0a
#75000000
1!
b0001000100010000 '
1(
1*
0+
1/
b0001000100010000 5
16
18
09
0=
1C
b0001000100010000 I
1J
1L
0M
b0001000100010000 Y
1Z
1\
0]
1a
0b
#76000000
0#
01
0E
#80000000
0!
0/
0C
0a
#85000000
1!
1#
0(
0*
1/
11
06
08
0B
1C
1E
0J
0L
0R
0Z
0\
1a
0g
0i
#90000000
0!
0/
0C
0a
#95000000
1!
1(
1)
1/
16
17
1C
1J
1K
b10 V
1Z
1[
1a
#96000000
0#
01
0E
#100000000
0!
0/
0C
0a
#105000000
1!
1#
1$
b1010101111001101 &
0(
0)
1/
11
12
b1010101111001101 4
06
07
1C
1E
1F
b1010101111001101 H
0J
0K
0Z
0[
1a
#110000000
0!
0/
0C
0a
#115000000
1!
1)
1+
1,
b1010101111001101 .
1/
17
19
1:
b1010101111001101 <
1=
1>
b1010101111001101 @
1C
1K
1M
1N
b1010101111001101 P
b1010101111001101 T
1U
b11 V
1[
1]
1^
b1010101111001101 `
1a
1b
1c
b1010101111001101 e
#120000000
0!
0/
0C
0a
#125000000
1!
0)
1/
07
b1010101111001101 A
1B
1C
0K
b1010101111001101 Q
1R
0[
1a
b1010101111001101 f
1g
b1010101111001101 h
1i
#130000000
0!
0/
0C
0a
#135000000
1!
1(
0+
0,
1/
16
09
0:
0=
0>
1C
1J
0M
0N
1Z
0]
0^
1a
0b
0c
#136000000
0#
0$
01
02
0E
0F
#140000000
0!
0/
0C
0a
#145000000
1!
1#
b0000000000000000 &
0(
1/
11
b0000000000000000 4
06
0B
1C
1E
b0000000000000000 H
0J
0R
0Z
1a
0g
0i
#150000000
0!
0/
0C
0a
#155000000
1!
b1010101111001101 '
1(
1)
1/
b1010101111001101 5
16
17
1C
b1010101111001101 I
1J
1K
b0000000000000000 T
0U
b10 V
b1010101111001101 Y
1Z
1[
1a
#156000000
0#
01
0E
#160000000
0!
0/
0C
0a
#165000000
1!
1#
b0000000000100000 %
0(
0)
1/
11
b0000000000100000 3
06
07
1C
1E
b0000000000100000 G
0J
0K
0Z
0[
1a
#170000000
0!
0/
0C
0a
#175000000
1!
1*
1+
b0000000000100000 -
1/
18
19
b0000000000100000 ;
1=
b0000000000100000 ?
b0000000000000000 @
1C
1L
1M
b0000000000100000 O
b0000000000000000 P
b0000000000100000 S
b000000000010 X
1\
1]
b0000000000100000 _
b0000000000000000 `
1a
1b
b0000000000100000 d
b0000000000000000 e
#180000000
0!
0/
0C
0a
#185000000
1!
0*
b0001001000100000 .
1/
08
b0001001000100000 <
b0001001000100000 A
1B
1C
0L
b0001001000100000 Q
1R
0\
1a
b0001001000100000 f
1g
b0001001000100000 h
1i
#190000000
0!
0/
0C
0a
#195000000
1!
1/
1C
1a
#200000000
0!
0/
0C
0a
#205000000
1!
b0001001000100000 '
1(
1*
0+
1/
b0001001000100000 5
16
18
09
0=
1C
b0001001000100000 I
1J
1L
0M
b0001001000100000 Y
1Z
1\
0]
1a
0b
#206000000
0#
01
0E
#210000000
0!
0/
0C
0a
#215000000
1!
1#
b0000000000110000 %
0(
0*
1/
11
b0000000000110000 3
06
08
0B
1C
1E
b0000000000110000 G
0J
0L
0R
0Z
0\
1a
0g
0i
#220000000
0!
0/
0C
0a
#225000000
1!
1*
1+
b0000000000110000 -
1/
18
19
b0000000000110000 ;
1=
b0000000000110000 ?
1C
1L
1M
b0000000000110000 O
b0000000000110000 S
b1 V
b000000000011 X
1\
1]
b0000000000110000 _
1a
1b
b0000000000110000 d
#230000000
0!
0/
0C
0a
#235000000
1!
0*
b0001001100110000 .
1/
08
b0001001100110000 <
b0001001100110000 A
1B
1C
0L
b0001001100110000 Q
1R
0\
1a
b0001001100110000 f
1g
b0001001100110000 h
1i
#240000000
0!
0/
0C
0a
#245000000
1!
1/
1C
1a
#250000000
0!
0/
0C
0a
#255000000
1!
b0001001100110000 '
1(
1*
0+
1/
b0001001100110000 5
16
18
09
0=
1C
b0001001100110000 I
1J
1L
0M
b0001001100110000 Y
1Z
1\
0]
1a
0b
#256000000
0#
01
0E
#260000000
0!
0/
0C
0a
#265000000
1!
1#
b0000000001000000 %
0(
0*
1/
11
b0000000001000000 3
06
08
0B
1C
1E
b0000000001000000 G
0J
0L
0R
0Z
0\
1a
0g
0i
#270000000
0!
0/
0C
0a
#275000000
1!
1*
1+
b0000000001000000 -
1/
18
19
b0000000001000000 ;
1=
b0000000001000000 ?
1C
1L
1M
b0000000001000000 O
b0000000001000000 S
b0 V
b000000000100 X
1\
1]
b0000000001000000 _
1a
1b
b0000000001000000 d
#280000000
0!
0/
0C
0a
#285000000
1!
0*
b0001010001000000 .
1/
08
b0001010001000000 <
b0001010001000000 A
1B
1C
0L
b0001010001000000 Q
1R
0\
1a
b0001010001000000 f
1g
b0001010001000000 h
1i
#290000000
0!
0/
0C
0a
#295000000
1!
1/
1C
1a
#300000000
0!
0/
0C
0a
#305000000
1!
b0001010001000000 '
1(
1*
0+
1/
b0001010001000000 5
16
18
09
0=
1C
b0001010001000000 I
1J
1L
0M
b0001010001000000 Y
1Z
1\
0]
1a
0b
#306000000
0#
01
0E
#310000000
0!
0/
0C
0a
#315000000
1!
1#
b0000000001010000 %
0(
0*
1/
11
b0000000001010000 3
06
08
0B
1C
1E
b0000000001010000 G
0J
0L
0R
0Z
0\
1a
0g
0i
#320000000
0!
0/
0C
0a
#325000000
1!
1*
1+
b0000000001010000 -
1/
18
19
b0000000001010000 ;
1=
b0000000001010000 ?
1C
1L
1M
b0000000001010000 O
b0000000001010000 S
b11 V
b000000000101 X
1\
1]
b0000000001010000 _
1a
1b
b0000000001010000 d
#330000000
0!
0/
0C
0a
#335000000
1!
0*
b0001010101010000 .
1/
08
b0001010101010000 <
b0001010101010000 A
1B
1C
0L
b0001010101010000 Q
1R
0\
1a
b0001010101010000 f
1g
b0001010101010000 h
1i
#340000000
0!
0/
0C
0a
#345000000
1!
1/
1C
1a
#350000000
0!
0/
0C
0a
#355000000
1!
b0001010101010000 '
1(
1*
0+
1/
b0001010101010000 5
16
18
09
0=
1C
b0001010101010000 I
1J
1L
0M
b0001010101010000 Y
1Z
1\
0]
1a
0b
#356000000
0#
01
0E
#360000000
0!
0/
0C
0a
#365000000
1!
1#
b0000000000010000 %
0(
0*
1/
11
b0000000000010000 3
06
08
0B
1C
1E
b0000000000010000 G
0J
0L
0R
0Z
0\
1a
0g
0i
#370000000
0!
0/
0C
0a
#375000000
1!
1*
1+
b0000000000010000 -
1/
18
19
b0000000000010000 ;
1=
b0000000000010000 ?
1C
1L
1M
b0000000000010000 O
b0000000000010000 S
b10 V
b000000000001 X
1\
1]
b0000000000010000 _
1a
1b
b0000000000010000 d
#380000000
0!
0/
0C
0a
#385000000
1!
0*
b1010101111001101 .
1/
08
b1010101111001101 <
b1010101111001101 A
1B
1C
0L
b1010101111001101 Q
1R
0\
1a
b1010101111001101 f
1g
b1010101111001101 h
1i
#390000000
0!
0/
0C
0a
#395000000
1!
1/
1C
1a
#400000000
0!
0/
0C
0a
#405000000
1!
b1010101111001101 '
1(
1*
0+
1/
b1010101111001101 5
16
18
09
0=
1C
b1010101111001101 I
1J
1L
0M
b1010101111001101 Y
1Z
1\
0]
1a
0b
#406000000
0#
01
0E
#410000000
0!
0/
0C
0a
#415000000
1!
0(
0*
1/
06
08
0B
1C
0J
0L
0R
0Z
0\
1a
0g
0i
